<GOC>
 <MUC_TU Loai_tu="" Noi_dung="">
  <Y_NGHIA Minh_hoa="" Noi_dung="ong một số tổ hợp). Bắp thịt, về" />
  </MUC_TU>
 <MUC_TU Loai_tu="" Noi_dung="u hiện của thể lực.">
  <Y_NGHIA Minh_hoa="Thử gân anh" Noi_dung="" />
  </MUC_TU>
 <MUC_TU Loai_tu="" Noi_dung="út">
  <Y_NGHIA Minh_hoa="" Noi_dung="(kng.; thử sức xem có khoẻ" />
  </MUC_TU>
 <MUC_TU Loai_tu="" Noi_dung="2n gân*.">
  <Y_NGHIA Minh_hoa="Nắn gân&quot;. A Bộ phận" Noi_dung="" />
  </MUC_TU>
 <MUC_TU Loai_tu="" Noi_dung="rõ lên ở trên một bề mặt như">
  <Y_NGHIA Minh_hoa="" Noi_dung="" />
  </MUC_TU>
 <MUC_TU Loai_tu="" Noi_dung="ờng gân.">
  <Y_NGHIA Minh_hoa="Gân lá (bộ mạch dẫn" Noi_dung="" />
  </MUC_TU>
 <MUC_TU Loai_tu="" Noi_dung="ên ở mặt 1á).">
  <Y_NGHIA Minh_hoa="Lá lúa có gân song" Noi_dung="" />
  </MUC_TU>
 <MUC_TU Loai_tu="" Noi_dung="ng tảng đá có gân.">
  <Y_NGHIA Minh_hoa="" Noi_dung="" />
  </MUC_TU>
 <MUC_TU Loai_tu="" Noi_dung="(kng.).">
  <Y_NGHIA Minh_hoa="" Noi_dung="Vươn cổ ra phía trước làm" />
  </MUC_TU>
 <MUC_TU Loai_tu="" Noi_dung="rờng gân ở cổ căng lên và nổi rõ,">
  <Y_NGHIA Minh_hoa="" Noi_dung="" />
  </MUC_TU>
 <MUC_TU Loai_tu="" Noi_dung="ng tả cái vẻ đưa hết sức ra một">
  <Y_NGHIA Minh_hoa="" Noi_dung="" />
  </MUC_TU>
 <MUC_TU Loai_tu="" Noi_dung="z bình.">
  <Y_NGHIA Minh_hoa="" Noi_dung="Gân cổ cãi bằng được." />
  </MUC_TU>
 <MUC_TU Loai_tu="" Noi_dung=".">
  <Y_NGHIA Minh_hoa="" Noi_dung="Gân và xương, dùng chỉ phần" />
  </MUC_TU>
 <MUC_TU Loai_tu="" Noi_dung="›ng thể lực con người.">
  <Y_NGHIA Minh_hoa="Gân cốt" Noi_dung="" />
  </MUC_TU>
 <MUC_TU Loai_tu="" Noi_dung="Ốm dậy cảm thấy gân cốt rã rời.">
  <Y_NGHIA Minh_hoa="" Noi_dung="" />
  </MUC_TU>
 <MUC_TU Loai_tu="danh từ" Noi_dung=":1">
  <Y_NGHIA Minh_hoa="0d). Đường gân nổi lên" Noi_dung="" />
  </MUC_TU>
 <MUC_TU Loai_tu="" Noi_dung="1a">
  <Y_NGHIA Minh_hoa="Gân guốc nổi" Noi_dung="(nói khái quát)." />
  </MUC_TU>
 <MUC_TU Loai_tu="tính từ" Noi_dung="t.II">
  <Y_NGHIA Minh_hoa="" Noi_dung="1 Có nhiều đường gân thớ" />
  </MUC_TU>
 <MUC_TU Loai_tu="" Noi_dung="`n, trông thô, nhưng rắn chắc.">
  <Y_NGHIA Minh_hoa="" Noi_dung="" />
  </MUC_TU>
 <MUC_TU Loai_tu="" Noi_dung="nh tay gân guốc.">
  <Y_NGHIA Minh_hoa="" Noi_dung="2 Rắn rỏi, cứng" />
  </MUC_TU>
 <MUC_TU Loai_tu="" Noi_dung="1nh gân guốc.">
  <Y_NGHIA Minh_hoa="" Noi_dung="" />
  </MUC_TU>
 <MUC_TU Loai_tu="danh từ" Noi_dung="">
  <Y_NGHIA Minh_hoa="" Noi_dung="Sức mạnh trong người dồn" />
  </MUC_TU>
 <MUC_TU Loai_tu="" Noi_dung="n việc gì nặng nhọc.">
  <Y_NGHIA Minh_hoa="Lấy hết gân" Noi_dung="" />
  </MUC_TU>
 <MUC_TU Loai_tu="" Noi_dung="ng đá.">
  <Y_NGHIA Minh_hoa="" Noi_dung="" />
  </MUC_TU>
 <MUC_TU Loai_tu="" Noi_dung="Ở vị trí chỉ cách một khoảng">
  <Y_NGHIA Minh_hoa="" Noi_dung="" />
  </MUC_TU>
 <MUC_TU Loai_tu="" Noi_dung="n tương đối ngắn.">
  <Y_NGHIA Minh_hoa="" Noi_dung="Cửa hàng ở" />
  </MUC_TU>
 <MUC_TU Loai_tu="" Noi_dung="-àm uiệc gần nhà.">
  <Y_NGHIA Minh_hoa="" Noi_dung="Ngồi xích lại" />
  </MUC_TU>
 <MUC_TU Loai_tu="" Noi_dung="">
  <Y_NGHIA Minh_hoa="" Noi_dung="2 Ở vào lúc chỉ cằn một khoảng" />
  </MUC_TU>
 <MUC_TU Loai_tu="" Noi_dung="tương đối ngắn nữa là đến thời">
  <Y_NGHIA Minh_hoa="" Noi_dung="" />
  </MUC_TU>
 <MUC_TU Loai_tu="" Noi_dung="đó.">
  <Y_NGHIA Minh_hoa="Gần đến giờ" Noi_dung="Trời gần sáng." />
  </MUC_TU>
 <MUC_TU Loai_tu="" Noi_dung="Việc làm gần xong.">
  <Y_NGHIA Minh_hoa="" Noi_dung="3 Ở mức chỉ" />
  </MUC_TU>
 <MUC_TU Loai_tu="" Noi_dung="t nữa thôi là đạt đến số lượng,">
  <Y_NGHIA Minh_hoa="" Noi_dung="" />
  </MUC_TU>
 <MUC_TU Loai_tu="" Noi_dung="nào đó.">
  <Y_NGHIA Minh_hoa="" Noi_dung="Sách dày gần trang." />
  </MUC_TU>
 <MUC_TU Loai_tu="" Noi_dung="chín.">
  <Y_NGHIA Minh_hoa="" Noi_dung="Đi nhanh gân như chạy." />
  </MUC_TU>
 <MUC_TU Loai_tu="" Noi_dung="thái có nhiều điểm giống nhau,">
  <Y_NGHIA Minh_hoa="" Noi_dung="" />
  </MUC_TU>
 <MUC_TU Loai_tu="" Noi_dung="rới nhau hơn là khác nhau.">
  <Y_NGHIA Minh_hoa="" Noi_dung="Phát" />
  </MUC_TU>
 <MUC_TU Loai_tu="" Noi_dung="Mới chuẩn.">
  <Y_NGHIA Minh_hoa="" Noi_dung="Quan điểm của hai" />
  </MUC_TU>
 <MUC_TU Loai_tu="" Noi_dung="hau.">
  <Y_NGHIA Minh_hoa="" Noi_dung="5 (dùng hạn chế trong một" />
  </MUC_TU>
 <MUC_TU Loai_tu="" Noi_dung=".">
  <Y_NGHIA Minh_hoa="" Noi_dung="Có cùng chung một ông tổ, chỉ" />
  </MUC_TU>
 <MUC_TU Loai_tu="" Noi_dung="đời.">
  <Y_NGHIA Minh_hoa="Bà con gần. Có họ gần với" Noi_dung="" />
  </MUC_TU>
 <MUC_TU Loai_tu="" Noi_dung="hoặc đg.).">
  <Y_NGHIA Minh_hoa="" Noi_dung="Có điều kiện thường" />
  </MUC_TU>
 <MUC_TU Loai_tu="" Noi_dung="› xúc, có quan hệ với nhau hàng">
  <Y_NGHIA Minh_hoa="" Noi_dung="" />
  </MUC_TU>
 <MUC_TU Loai_tu="" Noi_dung="g sinh hoạt, công tác.">
  <Y_NGHIA Minh_hoa="" Noi_dung="Về quê có" />
  </MUC_TU>
 <MUC_TU Loai_tu="" Noi_dung="ằn nông dân.">
  <Y_NGHIA Minh_hoa="" Noi_dung="Một người dễ gân" />
  </MUC_TU>
 <MUC_TU Loai_tu="động từ" Noi_dung="(đg.). I">
  <Y_NGHIA Minh_hoa="Tác phong gân quân chúng. Sống giản dị, gần anh em." Noi_dung="(kng.).Có quan hệ tốt, thường hiểu rõ tâm tư, tình cảm và cảm thông sâu sắc (với người dưới mình)." />
  </MUC_TU>
 <MUC_TU Loai_tu="tính từ" Noi_dung="gần cận">
  <Y_NGHIA Minh_hoa="Những người gân cận." Noi_dung="(kng.; ít dùng). Gần, thường ở bên cạnh nhau (nói khái quát)." />
  </MUC_TU>
 <MUC_TU Loai_tu="(khẩu ngữ)." Noi_dung="gần chùa gọi bụt bằng anh">
  <Y_NGHIA Minh_hoa="" Noi_dung="Ví trường hợp ở gần, hăng ngày quen tiếp xúc với người cấp trên, cho nên sinh nhờn, thiếu kính nể, thiếu lễ độ." />
  </MUC_TU>
 <MUC_TU Loai_tu="" Noi_dung="gần đất xa trời Ở vào tuổi không còn ¡">
  <Y_NGHIA Minh_hoa="" Noi_dung="sống được lâu nữa." />
  </MUC_TU>
 <MUC_TU Loai_tu="tính từ" Noi_dung="gần gặn">
  <Y_NGHIA Minh_hoa="Đường đi chẳng gần gặn gì." Noi_dung="(khẩu ngữ). Gần, không xa (nói khái quát)." />
  </MUC_TU>
 <MUC_TU Loai_tu="tính từ" Noi_dung="gần gũi I">
  <Y_NGHIA Minh_hoa="Người cộng tác gần m gũi. Có quan hệ họ hàng gần gũi. lđg 16d,. (Người có quan hệ thân thiết) sống bên . nhau. # có dịp gần gũi uợ con. 2 Có quan hệ tốt, thường xuyên có tiếp xúc, hiểu rõ | sinh hoạt, tâm tư, tình cảm và cảm thông | sâu sắc với người dưới mình. Tác phong | gân gũi quân chúng. |" Noi_dung="(hoặc động từ). Gần nhau, về quan E==z=&lt;=== hệ tinh thần, tình cảm hoặc quan hệ họ E=xs— hàng (nói khái quát)." />
  </MUC_TU>
 <MUC_TU Loai_tu="xem" Noi_dung="gần gụi (ph.).">
  <Y_NGHIA Minh_hoa="" Noi_dung="gần gũi. |" />
  </MUC_TU>
 <MUC_TU Loai_tu="" Noi_dung="gần kể miệng lỗ">
  <Y_NGHIA Minh_hoa="Vkiến của bạn đọc gân xa." Noi_dung="(tht.). Như gần đất xa trời. gần xa tính từ Gần cũng như xa, khắp mọi nơi." />
  <Y_NGHIA Minh_hoa="Xa xôi cách trở. Thương nhau chẳng quản gần za... (ca dao)." Noi_dung="(kết hợp hạn chế)." />
  <Y_NGHIA Minh_hoa="xa, hết chuyện này đến chuyện nọ, đủ cả mọi chuyện. Chuyện gân xa." Noi_dung="(jd.). Gần và" />
  </MUC_TU>
 <MUC_TU Loai_tu="động từ" Noi_dung="gấp,">
  <Y_NGHIA Minh_hoa="Gấp quân áo. Gấp sách lại. Tờ báo gấp làm tư." Noi_dung="Làm cho một vật trở thành có hai hay nhiều lớp, nhiều khúc chồng sát lên nhau để cho gọn lại, khi mở ra vẫn nguyên vẹn như cũ." />
  </MUC_TU>
 <MUC_TU Loai_tu="động từ" Noi_dung="gấp;">
  <Y_NGHIA Minh_hoa="Sản lượng tăng gấp đôi. Hơn gấp ba lần." Noi_dung="Có số lượng hoặc mức độ bằng bao nhiêu lần đó khi so sánh." />
  </MUC_TU>
 <MUC_TU Loai_tu="tính từ" Noi_dung="gấp;">
  <Y_NGHIA Minh_hoa="Có việc gấp phải đi" Noi_dung="1 Cần được làm, được giải quyết trong một thời gian tương đối ngắn, không cho phép để chậm trễ." />
  </MUC_TU>
 </GOC>
