<GOC>
 <MUC_TU Loai_tu="" Noi_dung="thiếu sự tế nhị, sự nhã nhặn tối thiểu.">
  <Y_NGHIA Minh_hoa="Ăn nói sống sượng." Noi_dung="Cái nhìn sống sượng." />
  </MUC_TU>
 <MUC_TU Loai_tu="(khẩu ngữ)." Noi_dung="sống tết chết giỗ">
  <Y_NGHIA Minh_hoa="" Noi_dung="Còn sống thì biếu quà những ngày tết, mà chết đi thì nhớ cúng giỗ; tỏ ra nhớ ơn mãi mãi." />
  </MUC_TU>
 <MUC_TU Loai_tu="động từ" Noi_dung="sống thác">
  <Y_NGHIA Minh_hoa="Sống hay chết. Sống thác có nhau." Noi_dung="(ít dùng)." />
  <Y_NGHIA Minh_hoa="Sống thác quản chỉ." Noi_dung="(cũ; văn chương). Chết đi; chết." />
  </MUC_TU>
 <MUC_TU Loai_tu="danh từ" Noi_dung="sống trâu">
  <Y_NGHIA Minh_hoa="Đường sống trâu. Vành sống trâu." Noi_dung="(dùng phụ sau danh từ). Ví những chỗ gỗ cao lên theo chiều dọc của đường đất, hình như sống lưng con trâu." />
  </MUC_TU>
 <MUC_TU Loai_tu="xem" Noi_dung="sốp phơ">
  <Y_NGHIA Minh_hoa="" Noi_dung="sôpphơ." />
  </MUC_TU>
 <MUC_TU Loai_tu="tính từ" Noi_dung="sộp">
  <Y_NGHIA Minh_hoa="Khách sộp. Vớ được món Sộp." Noi_dung="(khẩu ngữ). Sang, tỏ ra nhiều tiền và hào phóng." />
  </MUC_TU>
 <MUC_TU Loai_tu="danh từ" Noi_dung="sôpphơ cũng viết sốp phơ.">
  <Y_NGHIA Minh_hoa="" Noi_dung="(cũ). Người làm nghề lái xe ôtô; tài xế." />
  </MUC_TU>
 <MUC_TU Loai_tu="động từ" Noi_dung="sốt,">
  <Y_NGHIA Minh_hoa="Bị sốt cao. Dứt cơn sốt. Hâm hấp sốt." Noi_dung="Tăng nhiệt độ cơ thể lên quá mức bình thường, do bị bệnh." />
  </MUC_TU>
 <MUC_TU Loai_tu="tính từ" Noi_dung="sốt,">
  <Y_NGHIA Minh_hoa="Cơm nóng canh sốt." Noi_dung="(id.; thường dùng đi đôi với nóng). (Cơm, canh) còn đang nóng, vừa mới bắc ở bếp xuống." />
  </MUC_TU>
 <MUC_TU Loai_tu="trợ từ" Noi_dung="sốt,">
  <Y_NGHIA Minh_hoa="" Noi_dung="(kng.; dùng ở cuối câu phủ định). Từ biểu thị ý nhấn mạnh sự phủ định hoàn toàn; sất. Không có gì sốt." />
  </MUC_TU>
 <MUC_TU Loai_tu="tính từ" Noi_dung="sốt dẻo">
  <Y_NGHIA Minh_hoa="Tin sốt dẻo. Tính chất thời sự sốt dóo0." Noi_dung="(kng,). (Tin tức) rất mới, vừa mới nhận được." />
  </MUC_TU>
 <MUC_TU Loai_tu="danh từ" Noi_dung="sốt rét">
  <Y_NGHIA Minh_hoa="" Noi_dung="Bệnh lây do một loại kí sinh trùng truyền qua muỗi anophel gây nên những cơn rét, nóng có chu kì, làm huỷ hoại nhiều hồng cầu." />
  </MUC_TU>
 <MUC_TU Loai_tu="động từ" Noi_dung="sốt ruột">
  <Y_NGHIA Minh_hoa="Ở trạng thái nôn nóng, không yên lòng. Sốt ruột chờ tin. Phải bình tĩnh, đừng sốt ruột." Noi_dung="" />
  </MUC_TU>
 <MUC_TU Loai_tu="tính từ" Noi_dung="sốt sắng">
  <Y_NGHIA Minh_hoa="Sốt sắng với công việc chung." Noi_dung="Tỏ ra có nhiệt tình với công việc nào đó, không tính thiệt hơn. Sốt sắng giúp đỡ bạn. Sốt sắng hưởng ứng." />
  </MUC_TU>
 <MUC_TU Loai_tu="phụ từ" Noi_dung="sốt sột">
  <Y_NGHIA Minh_hoa="" Noi_dung="(thgt.; dùng phụ sau động từ). Ngay lập tức. Làm sốt sột." />
  </MUC_TU>
 <MUC_TU Loai_tu="tính từ" Noi_dung="sốt vó">
  <Y_NGHIA Minh_hoa="Lo sốt uó vì thời hạn sắp hết." Noi_dung="(Kg.; thường dùng sau lo). Ở trạng thái cuống lên." />
  </MUC_TU>
 <MUC_TU Loai_tu="danh từ" Noi_dung="sốt xuất huyết">
  <Y_NGHIA Minh_hoa="" Noi_dung="Bệnh dịch do một loại virus gây nên, triệu chứng là sốt và chảy máu." />
  </MUC_TU>
 <MUC_TU Loai_tu="(ít dùng)." Noi_dung="sột sệt t">
  <Y_NGHIA Minh_hoa="Đất sột sệt như bùn ao." Noi_dung="Sẻn sệt, hơi quánh lại (thường nói về bùn)." />
  </MUC_TU>
 <MUC_TU Loai_tu="tính từ" Noi_dung="sột soạt">
  <Y_NGHIA Minh_hoa="Ngòi bút sột soạt trên giấy. Gió thối, tiếng lá khô sột soạt. Chuột chạy Sột soạt trên mái nhà." Noi_dung="Từ mô phỏng tiếng khua động nhẹ của những vật khô, mỏng, cứng khi chạm nhau." />
  </MUC_TU>
 <MUC_TU Loai_tu="tính từ" Noi_dung="sôvanh cũng viết sô uanh.">
  <Y_NGHIA Minh_hoa="" Noi_dung="Thuộc về chủ nghĩa sôvanh, có tính chất của chủ nghĩa sôvanh. Tư tưởng sôuanh nước lớn." />
  </MUC_TU>
 <MUC_TU Loai_tu="động từ" Noi_dung="sơ,">
  <Y_NGHIA Minh_hoa="" Noi_dung="(khẩu ngữ). Dùng đũa khuấy qua cho đều nồi cơm đang sôi. Sơ cơm." />
  </MUC_TU>
 <MUC_TU Loai_tu="" Noi_dung="sơ;t">
  <Y_NGHIA Minh_hoa="Nắm sơ tình hình. Nói sơ qua. Làm sơ." Noi_dung="(Làm việc gì) lướt qua một lượt, không kĩ càng, đầy đủ." />
  <Y_NGHIA Minh_hoa="Trước sơsau thân. Kế thân người sơ." Noi_dung="(¡d; thường dùng đi đôi với thân). Không thân, thường là mới quen biết." />
  </MUC_TU>
 <MUC_TU Loai_tu="tính từ" Noi_dung="sơ,">
  <Y_NGHIA Minh_hoa="" Noi_dung="(cũ; kết hợp hạn chế). Ở vào giai đoạn đầu, mới hình thành. Thời Lê sơ." />
  </MUC_TU>
 <MUC_TU Loai_tu="tính từ" Noi_dung="sơ bộ">
  <Y_NGHIA Minh_hoa="Theo ước tính sơ bộ. Sơ bộ rút ra một số kinh nghiệm." Noi_dung="Có tính chất bước đầu, trước cái khác hoặc chuẩn bị cho việc khác đầy đủ hơn, quan trọng hơn." />
  </MUC_TU>
 <MUC_TU Loai_tu="tính từ" Noi_dung="sơ cấp">
  <Y_NGHIA Minh_hoa="Toán học sơ cấp. Cán bộ sơ cấp. 2x. cuộn sơ cấp." Noi_dung="1 Thuộc cấp thấp nhất, dưới trung cấp." />
  </MUC_TU>
 <MUC_TU Loai_tu="động từ" Noi_dung="sơ chế">
  <Y_NGHIA Minh_hoa="Sơ chế chè búp trước khi đưa uề nhà máy." Noi_dung="Chế biến qua cho nguyên liệu thành ra bán thành phẩm." />
  </MUC_TU>
 <MUC_TU Loai_tu="động từ" Noi_dung="sơ cứu">
  <Y_NGHIA Minh_hoa="Sơ cứu người bị nạn." Noi_dung="Cấp cứu bước đầu." />
  </MUC_TU>
 <MUC_TU Loai_tu="tính từ" Noi_dung="sơ đẳng">
  <Y_NGHIA Minh_hoa="Thuộc bậc học thấp `nhất. Trường sơ đẳng." Noi_dung="(cũ)." />
  <Y_NGHIA Minh_hoa="Những kiến thức sơ đẳng. Nguyên tắc pháp H sơ đẳng." Noi_dung="Ở mức thấp nhất." />
  </MUC_TU>
 <MUC_TU Loai_tu="danh từ" Noi_dung="sơ đồ">
  <Y_NGHIA Minh_hoa="Sơ đồ mạng điện. Lập sơ đồ." Noi_dung="Hình vẽ quy ước, sơ lược, nhằm mô tả một đặc trưng nào đó của sự vật hay một quá trình nào đó." />
  </MUC_TU>
 <MUC_TU Loai_tu="tính từ" Noi_dung="sơ giản">
  <Y_NGHIA Minh_hoa="Một định nghĩa sơ giản." Noi_dung="(ít dùng). Sơ lược và đơn giản." />
  </MUC_TU>
 <MUC_TU Loai_tu="tính từ" Noi_dung="sơ giao">
  <Y_NGHIA Minh_hoa="" Noi_dung="(cũ). Mới quen nhau. Bạn sơ giao." />
  </MUC_TU>
 <MUC_TU Loai_tu="danh từ" Noi_dung="sơ học">
  <Y_NGHIA Minh_hoa="Trường sơ học. Bằng sơ học." Noi_dung="(thường dùng phụ sau danh từ). Cấp học thấp nhất trong hệ thống giáo dục thời thực dân Pháp." />
  </MUC_TU>
 <MUC_TU Loai_tu="danh từ" Noi_dung="sơ học yếu lược">
  <Y_NGHIA Minh_hoa="" Noi_dung="Những năm học dưới cùng trong cấp sơ học, trong hệ thống giáo dục thời thực dân Pháp (nói tổng quát)." />
  </MUC_TU>
 <MUC_TU Loai_tu="động từ" Noi_dung="sơ hở">
  <Y_NGHIA Minh_hoa="Lợi dụng sơ hở." Noi_dung="(hoặc danh từ). Sơ ý, không đề phòng cẩn thận. Sơ hở một chút là hỏng việc." />
  </MUC_TU>
 <MUC_TU Loai_tu="động từ" Noi_dung="sơ kết">
  <Y_NGHIA Minh_hoa="Sơ kết học kì. Sơ kết công tác sáu tháng." Noi_dung="Nhìn lại một phần hoặc một thời kì nào đó công việc đã làm để có sự đánh giá, rút ra những kết luận bước đầu." />
  </MUC_TU>
 <MUC_TU Loai_tu="tính từ" Noi_dung="sơ khai">
  <Y_NGHIA Minh_hoa="Thời kì sơ khai của xã hột." Noi_dung="Thuộc vào buổi đầu mới hình thành, mới được lập ra." />
  </MUC_TU>
 <MUC_TU Loai_tu="động từ" Noi_dung="sơ khảo">
  <Y_NGHIA Minh_hoa="" Noi_dung="Chấm lần thứ nhất trong các khoa thi thời phong kiến." />
  </MUC_TU>
 <MUC_TU Loai_tu="danh từ" Noi_dung="sơ kì cũng viết sơ kỳ.">
  <Y_NGHIA Minh_hoa="Sơ kì đồ đá cũ. Xã hội phong kiến sơ kì." Noi_dung="Giai đoạn đầu của một thời kì lịch sử hay của một chế độ xã hội." />
  </MUC_TU>
 <MUC_TU Loai_tu="động từ" Noi_dung="sơ kiến">
  <Y_NGHIA Minh_hoa="Gặp nhau lần đầu. Buổi sơ kiến." Noi_dung="(cũ)." />
  </MUC_TU>
 <MUC_TU Loai_tu="" Noi_dung="sơ kỷx. sơ kì.">
  <Y_NGHIA Minh_hoa="" Noi_dung="" />
  </MUC_TU>
 <MUC_TU Loai_tu="tính từ" Noi_dung="sơ lược">
  <Y_NGHIA Minh_hoa="Dàn ý sơ lược. Tiểu sử sơ lược. Giới thiệu sơ lược nội dung tác phẩm." Noi_dung="Chỉ trên những nét lớn, nét chính, bỏ qua các chỉ tiết." />
  <Y_NGHIA Minh_hoa="dung, nghèo nàn uễ hình thức. sơ mỉ xem sơmi." Noi_dung="Rất chung chung, thiếu chi tiết cụ thể, không kĩ, không sâu. Còn sơ lược về nội" />
  </MUC_TU>
 <MUC_TU Loai_tu="động từ" Noi_dung="sơ nhiễm">
  <Y_NGHIA Minh_hoa="Sơ nhiễm lao." Noi_dung="Bị tổn thương ban đầu ở một bộ phận cơ thể (thường nói về bệnh lao ở trẻ em)." />
  </MUC_TU>
 <MUC_TU Loai_tu="tính từ" Noi_dung="sơ sài">
  <Y_NGHIA Minh_hoa="Đồ đạc sơ sài. Nhà lá sơ sài." Noi_dung="Đơn sơ và ít ỏi." />
  <Y_NGHIA Minh_hoa="Bài làm sơ sài. Công tác chuẩn bị quá sơ sài." Noi_dung="Qua loa, không kĩ." />
  </MUC_TU>
 <MUC_TU Loai_tu="tính từ" Noi_dung="sơ sinh">
  <Y_NGHIA Minh_hoa="" Noi_dung="Mới đẻ ra. Trẻ sơ sinh." />
  </MUC_TU>
 <MUC_TU Loai_tu="danh từ" Noi_dung="sơ sót">
  <Y_NGHIA Minh_hoa="Như sai sót." Noi_dung="(ít dùng)." />
  </MUC_TU>
 <MUC_TU Loai_tu="tính từ" Noi_dung="sơ sơ">
  <Y_NGHIA Minh_hoa="Bị thương sơ sơ ở phần mềm. Chỉ biết sơ sơ thôi." Noi_dung="(kng.; thường dùng phụ sau động từ). Chỉ một phần nào, một chút ít thôi, không đáng kể." />
  </MUC_TU>
 <MUC_TU Loai_tu="động từ" Noi_dung="sơ suất">
  <Y_NGHIA Minh_hoa="Do sơ suất mà hỏng uiệc. sơ tán động từ Tạm di chuyển người và của ra khỏi khu vực không an toàn để tránh tai nạn, thường là tai nạn chiến tranh. Sơ tán người già uà trẻ em. Sơ tán về nông thôn. Tạm thời sơ tán khi nước sông lên to." Noi_dung="(hoặc danh từ). Không cẩn thận, không chú ý đúng mức để có sai sót. Sơ suất trong cư xử." />
  </MUC_TU>
 <MUC_TU Loai_tu="động từ" Noi_dung="sơ thảo">
  <Y_NGHIA Minh_hoa="" Noi_dung="(hoặc danh từ). Thảo ra lần đầu, còn phải được sửa chữa cho hoàn chỉnh." />
  </MUC_TU>
 <MUC_TU Loai_tu="động từ" Noi_dung="sơ thẩm">
  <Y_NGHIA Minh_hoa="" Noi_dung="Xét xử một vụ án với tư cách là toà án ở cấp xử thấp nhất." />
  </MUC_TU>
 <MUC_TU Loai_tu="động từ" Noi_dung="sơ tuyển">
  <Y_NGHIA Minh_hoa="Bị loại ngay ở uòng sơ tuyển." Noi_dung="Tuyển chọn vòng đầu theo những yêu cầu tối thiểu. Phải qua sơ tuyển mới được thi chính thức." />
  </MUC_TU>
 <MUC_TU Loai_tu="động từ" Noi_dung="sơ ý">
  <Y_NGHIA Minh_hoa="Sơ ý một tí là hóng uiệc. Sơ ý nói lỡ lời." Noi_dung="Không để tâm, để ý đến trong chốc lát để xảy ra điều đáng tiếc." />
  </MUC_TU>
 <MUC_TU Loai_tu="danh từ" Noi_dung="sơ yếu">
  <Y_NGHIA Minh_hoa="Sơ yếu lí lịch." Noi_dung="(kết hợp hạn chế). Bản tóm tắt." />
  </MUC_TU>
 <MUC_TU Loai_tu="động từ" Noi_dung="sờ">
  <Y_NGHIA Minh_hoa="" Noi_dung="Đặt và di động nhẹ bàn tay trên bề mặt của vật để nhận biết bằng xúc giác. Sờ xem nóng hay lạnh." />
  <Y_NGHIA Minh_hoa="" Noi_dung="(xg,). Động đến, bắt tay làm. Không bao giờ sờ đến việc nhà." />
  </MUC_TU>
 <MUC_TU Loai_tu="" Noi_dung="sờ lên gáy">
  <Y_NGHIA Minh_hoa="" Noi_dung="Tự mình nhìn lại chính mình (cũng có thể thấy cái xấu mà mình tưởng chỉ người khác mới có)." />
  </MUC_TU>
 <MUC_TU Loai_tu="động từ" Noi_dung="sờ mó">
  <Y_NGHIA Minh_hoa="" Noi_dung="Sờ vào (nói khái quát). Sờ mó lung tung, làm hỏng hết! Chẳng chịu sờ mó uiệc gì cá (khẩu ngữ)." />
  </MUC_TU>
 <MUC_TU Loai_tu="(phương ngữ)." Noi_dung="sờ sâm">
  <Y_NGHIA Minh_hoa="" Noi_dung="x rờrâm." />
  </MUC_TU>
 <MUC_TU Loai_tu="động từ" Noi_dung="sờ soạng">
  <Y_NGHIA Minh_hoa="Đền tắt, sờ soạng tìm diêm." Noi_dung="Sờ chỗ này chỗ khác để tìm, do mắt không nhìn thấy (nói khái quát). Sờ soạng trong đêm tối." />
  </MUC_TU>
 <MUC_TU Loai_tu="(khẩu ngữ)." Noi_dung="sờ sờ t">
  <Y_NGHIA Minh_hoa="Khuyết điểm sờ sờ, còn cãi!" Noi_dung="Quá rõ ràng như bày ra trước mắt. Sự thật sờ sờ trước mắt." />
  </MUC_TU>
 <MUC_TU Loai_tu="động từ" Noi_dung="sờ sợ">
  <Y_NGHIA Minh_hoa="" Noi_dung="xem sợ (láy)." />
  </MUC_TU>
 <MUC_TU Loai_tu="tính từ" Noi_dung="sờ sững">
  <Y_NGHIA Minh_hoa="" Noi_dung="Như sững sờ." />
  </MUC_TU>
 </GOC>
