<GOC>
 <MUC_TU Loai_tu="tính từ" Noi_dung="chằm chằm">
  <Y_NGHIA Minh_hoa="Nhìn chầm chằm uào mặt khách." Noi_dung="(thường dùng phụ cho đg,). (Cách nhìn) chăm chú, thẳng và lâu không chớp, thường có ý dò xét." />
  </MUC_TU>
 <MUC_TU Loai_tu="tính từ" Noi_dung="chằm chặp,">
  <Y_NGHIA Minh_hoa="" Noi_dung="Như chằm chằm." />
  </MUC_TU>
 <MUC_TU Loai_tu="" Noi_dung="chằm chặp,">
  <Y_NGHIA Minh_hoa="" Noi_dung="(cũ, hoặc phương ngữ). x chằm chập. chặm động từ (phương ngữ). Thấm từng ít một cho khô. Chặm nước mắt. Kéo uạt áo chặm mỗ hôi." />
  </MUC_TU>
 <MUC_TU Loai_tu="danh từ" Noi_dung="chăn,">
  <Y_NGHIA Minh_hoa="Chiếc chăn len. Chăn bông. Chăn đơn." Noi_dung="Đồ dùng bằng vải, len, dạ, v.v. để đắp cho ấm." />
  </MUC_TU>
 <MUC_TU Loai_tu="động từ" Noi_dung="chăn;">
  <Y_NGHIA Minh_hoa="Chăn bò. Chăn ngông." Noi_dung="Đưa đi kiếm ăn và trông nom gia súc, gia cảm." />
  <Y_NGHIA Minh_hoa="Chăn tằm. Chăn trẻ (khẩu ngữ)." Noi_dung="Nuôi, chăm sóc (thường nói về tằm)." />
  </MUC_TU>
 <MUC_TU Loai_tu="phụ từ" Noi_dung="chăn chắn">
  <Y_NGHIA Minh_hoa="" Noi_dung="Như chân chặn." />
  </MUC_TU>
 <MUC_TU Loai_tu="động từ" Noi_dung="chăn dắt">
  <Y_NGHIA Minh_hoa="Chăn dắt trâu bò." Noi_dung="Chăn gia súc (nói khái quát)." />
  <Y_NGHIA Minh_hoa="Chăn dắt đàn em nhỏ." Noi_dung="(ít dùng). Trông nom, dìu dắt." />
  </MUC_TU>
 <MUC_TU Loai_tu="" Noi_dung="chăn đơn gối chiếc">
  <Y_NGHIA Minh_hoa="" Noi_dung="(cũ; văn chương). Tả cảnh cô đơn của người phụ nữ không chồng hoặc xa chồng." />
  </MUC_TU>
 <MUC_TU Loai_tu="động từ" Noi_dung="chăn gối">
  <Y_NGHIA Minh_hoa="Chưa chăn gối." Noi_dung="(cũ; văn chương). Chung chăn gối (nói tắt)." />
  </MUC_TU>
 <MUC_TU Loai_tu="động từ" Noi_dung="chăn nuôi">
  <Y_NGHIA Minh_hoa="Nuôi gia súc, gia cảm (nói khái quát). Chăn nuôi lợn. Trại chăn nuôi. Phát triển chăn nuôi." Noi_dung="(hoặc danh từ)." />
  </MUC_TU>
 <MUC_TU Loai_tu="danh từ" Noi_dung="chăn nuôi công nghiệp">
  <Y_NGHIA Minh_hoa="" Noi_dung="Chăn nuôi theo phương pháp kĩ thuật công nghiệp." />
  </MUC_TU>
 <MUC_TU Loai_tu="phụ từ" Noi_dung="chằn chặn">
  <Y_NGHIA Minh_hoa="" Noi_dung="(dùng hạn chế sau tính từ). (Bằng nhau) đều đặn đến mức không còn có thể hơn nữa. Bằng chằn chặn. Vuông chằn chặn." />
  </MUC_TU>
 <MUC_TU Loai_tu="danh từ" Noi_dung="chằn tỉnh">
  <Y_NGHIA Minh_hoa="" Noi_dung="Yêu quái trong truyện cổ tích thần thoại." />
  </MUC_TU>
 <MUC_TU Loai_tu="tính từ" Noi_dung="chấn">
  <Y_NGHIA Minh_hoa="Vừa chẵn hai nghìn đồng. Một trăm chẵn." Noi_dung="(Số) nguyên, tròn, không có phần lẻ." />
  <Y_NGHIA Minh_hoa="là số chẵn. Chợ họp uào ngày chẵn." Noi_dung="(Số) chia hết cho hai." />
  </MUC_TU>
 <MUC_TU Loai_tu="danh từ" Noi_dung="chấn lẻ">
  <Y_NGHIA Minh_hoa="Đánh chẵn lẻ." Noi_dung="Trò cờ bạc dùng sáu đồng tiền gieo xuống, tính số chấn hay lẻ của các mặt sấp, ngửa mà định được thua." />
  </MUC_TU>
 <MUC_TU Loai_tu="danh từ" Noi_dung="chắn,">
  <Y_NGHIA Minh_hoa="" Noi_dung="cũng nói chắn cạ. Lối chơi bài, cứ hai quân cùng loại hợp lại thành một &quot;chắn&quot;, khác loại hợp lại thành một &quot;cạ”. Đánh chắn. Đám chắn cạ." />
  </MUC_TU>
 <MUC_TU Loai_tu="động từ" Noi_dung="chắn; !">
  <Y_NGHIA Minh_hoa="Chắn dòng nước. Trồng cây chắn gió. Núi chắn ngang. Chắn đăng (dùng đăng chắn dòng nước để bắt cá)." Noi_dung="Ngăn giữ lại, không cho tiếp tục vận động theo một hướng nào đó." />
  <Y_NGHIA Minh_hoa="Chắn buồng làm hai phòng nhỏ. II danh từ Vật để ngăn lại, không cho qua. Nhấc chắn cho xe xuống phà." Noi_dung="(ít dùng). Ngăn để phân chia ra." />
  </MUC_TU>
 <MUC_TU Loai_tu="động từ" Noi_dung="chắn;">
  <Y_NGHIA Minh_hoa="Trồng trúc xin chớ chắn chỗi... (ca dao)." Noi_dung="(phương ngữ). Chặt đứt." />
  </MUC_TU>
 <MUC_TU Loai_tu="động từ" Noi_dung="chắn bóng">
  <Y_NGHIA Minh_hoa="" Noi_dung="Dùng tay ngăn bóng đập của đối phương ở trên lưới, trong bóng chuyên," />
  </MUC_TU>
 <MUC_TU Loai_tu="danh từ" Noi_dung="chắn bùn">
  <Y_NGHIA Minh_hoa="Chắn bùn xe đạp." Noi_dung="Tấm mỏng che trên bánh xe để bùn khỏi bắn lên." />
  </MUC_TU>
 <MUC_TU Loai_tu="" Noi_dung="chắn cạ d.x. chẳn..">
  <Y_NGHIA Minh_hoa="" Noi_dung="" />
  </MUC_TU>
 <MUC_TU Loai_tu="xem" Noi_dung="chẵn song">
  <Y_NGHIA Minh_hoa="chấn song." Noi_dung="" />
  </MUC_TU>
 <MUC_TU Loai_tu="danh từ" Noi_dung="chắn xích">
  <Y_NGHIA Minh_hoa="" Noi_dung="Tấm mỏng che xích xe đạp, môtô, v.v." />
  </MUC_TU>
 <MUC_TU Loai_tu="động từ" Noi_dung="chặn">
  <Y_NGHIA Minh_hoa="Lấy ghế chặn của. Chặn cho giấy khỏi bay. Cầu thủ chặn bóng." Noi_dung="Giữ chặt lại hoặc đè xuống, không cho tự do di động." />
  <Y_NGHIA Minh_hoa="Chặn đánh. Chặn các ngả đường. Ngăn chặn. Chặn đứng âm mưu." Noi_dung="Cản hẳn lại, làm cho sự hoạt động theo một hướng nào đó phải ngừng hẳn." />
  <Y_NGHIA Minh_hoa="Tiêm để chặn cơn sốt. Nói chặn*." Noi_dung="Ngăn ngừa trước, không cho xảy ra." />
  </MUC_TU>
 <MUC_TU Loai_tu="động từ" Noi_dung="chặn đứng">
  <Y_NGHIA Minh_hoa="" Noi_dung="Chặn ngay lại, làm cho phải ngừng ngay lại hoàn toàn. Chặn đứng cuộc tiến công. Nạn dịch bị chặn đứng." />
  </MUC_TU>
 <MUC_TU Loai_tu="động từ" Noi_dung="chặn hậu">
  <Y_NGHIA Minh_hoa="" Noi_dung="Đi sau cùng để chặn địch." />
  </MUC_TU>
 <MUC_TU Loai_tu="động từ" Noi_dung="chặn họng">
  <Y_NGHIA Minh_hoa="Ngăn chặn không cho nói hết ý. Nói chặn họng." Noi_dung="(thông tục)." />
  </MUC_TU>
 <MUC_TU Loai_tu="động từ" Noi_dung="chăng,">
  <Y_NGHIA Minh_hoa="Chăng giây. Chăng đền kết hoa. Nhện chăng tơ." Noi_dung="Như giăng›." />
  </MUC_TU>
 <MUC_TU Loai_tu="phụ từ" Noi_dung="chăng, !">
  <Y_NGHIA Minh_hoa="Nghe lỏm câu được câu chăng (có câu nghe được có câu không). Có chăng chỉ một mình anh ta biết." Noi_dung="(cũ; vch.; nay chỉ dùng trong một vài tổ hợp). Từ biểu thị ý phủ định; như chẳng, không." />
  <Y_NGHIA Minh_hoa="" Noi_dung="(thường dùng ở cuối câu). Từ biểu thị ý muốn hỏi," />
  </MUC_TU>
 <MUC_TU Loai_tu="" Noi_dung="">
  <Y_NGHIA Minh_hoa="Cuậm rồi chăng? Việc ấy nên chăng? Thuyền ơi ơó nhớ bến chăng?... (ca dao). lì trợ từ Từ biểu thị ý nhấn mạnh về điều vừa giả định, nhằm làm nổi bật điều muốn khẳng định. Khó đến mấy chăng nữa cũng không ngại." Noi_dung="tỏ ra còn nửa tin nửa ngờ." />
  </MUC_TU>
 <MUC_TU Loai_tu="động từ" Noi_dung="chẳng,">
  <Y_NGHIA Minh_hoa="" Noi_dung="Buộc từ bên nọ sang bên kia nhiều lần, không theo hàng lối nhất định, chỉ cốt cho thật chặt. Chằng gói hàng sau xe đạp." />
  </MUC_TU>
 <MUC_TU Loai_tu="động từ" Noi_dung="chằng;">
  <Y_NGHIA Minh_hoa="Tiêu chằng. Nhận chằng. Ăn chăng uay bửa." Noi_dung="(kng.; thường dùng phụ sau động từ). Lấy hoặc dùng của người khác một cách tuỳ tiện." />
  </MUC_TU>
 <MUC_TU Loai_tu="tính từ" Noi_dung="chẳng chằng">
  <Y_NGHIA Minh_hoa="Bé bám mẹ chằng chằng. Nhìn chằng chằng. Mặt trăng sánh với mặt trời, sao Hôm sánh với sao Mai chằng chằng (ca dao)." Noi_dung="Không rời, không dứt ra." />
  </MUC_TU>
 <MUC_TU Loai_tu="tính từ" Noi_dung="chẳng chéo">
  <Y_NGHIA Minh_hoa="Những đường chằng chéo trên bản đồ. Những mối liên hệ chằng chéo." Noi_dung="Thành những đường giao chéo nhau theo nhiều hướng khác nhau." />
  </MUC_TU>
 <MUC_TU Loai_tu="tính từ" Noi_dung="chẳng chịt">
  <Y_NGHIA Minh_hoa="Dây thép gai chằng chịt. Những mối quan hệ chăng chịt." Noi_dung="Thành những đường đan vào nhau dày đặc và không theo hàng lối nhất định. Mạng nhện chằng chịt." />
  </MUC_TU>
 <MUC_TU Loai_tu="phụ từ" Noi_dung="chẳng">
  <Y_NGHIA Minh_hoa="Mống bên đông, uồng bên tây, chẳng mưa dây thì bão giật (tục ngữ). Một người làm chẳng nổi. Thực tế đã chẳng chứng mình điều đó sao? Việc ấy ai chẳng biết (ai cũng biết)." Noi_dung="Từ biểu thị ý phủ định được nhấn mạnh (dứt khoát hơn không)." />
  </MUC_TU>
 <MUC_TU Loai_tu="trợ từ" Noi_dung="chẳng">
  <Y_NGHIA Minh_hoa="Ngỡ là ai, chẳng hoá ra lại là anh! Chẳng thà như thế còn hơn. Có xe, chẳng tội gì mà đi bộ. Chẳng mấy khi*" Noi_dung="(kng.; dùng hạn chế trong một số tổ hợp). Từ biểu thị ý nhấn mạnh thêm về sắc thái nghĩa của từ hoặc tổ hợp từ đứng liền sau." />
  </MUC_TU>
 <MUC_TU Loai_tu="" Noi_dung="chẳng bù">
  <Y_NGHIA Minh_hoa="Hôm nay nắng to, chẳng bù uới hôm qua mưa suốt ngày." Noi_dung="(dùng ở đầu câu hoặc đầu phân câu). Tổ hợp biểu thị điều sắp nói là trường hợp không tốt trái ngược lại, nêu ra để đối chiếu làm nổi bật trường hợp vừa được nói đến; không so sánh được, vì khác hẳn." />
  </MUC_TU>
 <MUC_TU Loai_tu="tính từ" Noi_dung="chẳng đâu vào đâu">
  <Y_NGHIA Minh_hoa="" Noi_dung="Như không đâu pào đâu." />
  </MUC_TU>
 <MUC_TU Loai_tu="" Noi_dung="chẳng hạn">
  <Y_NGHIA Minh_hoa="Có nhiều ưu điểm, chẳng hạn như cần cù, giản dị. So với năm ngoái chẳng hạn thì tiến bộ hơn nhiều." Noi_dung="Tổ hợp biểu thị ý nhấn mạnh về cái được dẫn chứng, được nêu làm thí dụ." />
  </MUC_TU>
 <MUC_TU Loai_tu="xem" Noi_dung="chẳng là (kng.).">
  <Y_NGHIA Minh_hoa="" Noi_dung="chả là." />
  </MUC_TU>
 <MUC_TU Loai_tu="phụ từ" Noi_dung="chẳng lẽ">
  <Y_NGHIA Minh_hoa="Chẳng lẽ làm thỉnh. Anh ấy về, chẳng lẽ tôi lại không biết?" Noi_dung="(dùng làm phần phụ trong câu). Không có lí nào; lẽ nào." />
  </MUC_TU>
 <MUC_TU Loai_tu="(khẩu ngữ)." Noi_dung="chẳng mấy chốc">
  <Y_NGHIA Minh_hoa="Là” ăn như thế chẳng mấy chốc mà phá sản." Noi_dung="Chẳng bao lâu." />
  </MUC_TU>
 <MUC_TU Loai_tu="(khẩu ngữ)." Noi_dung="chẳng mấy khi">
  <Y_NGHIA Minh_hoa="Chẳng mấy khi anh đến chơi." Noi_dung="Ít có địp, ít khi." />
  </MUC_TU>
 <MUC_TU Loai_tu="(khẩu ngữ)." Noi_dung="chẳng mấy nỗi">
  <Y_NGHIA Minh_hoa="Máy móc như thế này, dùng chẳng mấy nôi thì hỏng." Noi_dung="Chẳng lâu gì, chẳng bao lâu." />
  </MUC_TU>
 <MUC_TU Loai_tu="" Noi_dung="chẳng nhẽ">
  <Y_NGHIA Minh_hoa="" Noi_dung="(ph., hoặc khẩu ngữ). x chẳng lẽ." />
  </MUC_TU>
 <MUC_TU Loai_tu="xem" Noi_dung="chẳng những">
  <Y_NGHIA Minh_hoa="" Noi_dung="không những." />
  </MUC_TU>
 <MUC_TU Loai_tu="kết từ" Noi_dung="chẳng nữa">
  <Y_NGHIA Minh_hoa="Tranh thủ gặt cho xong, chẳng nữa trời mưa, lúa hỏng hết." Noi_dung="(khẩu ngữ). Nếu không vậy, nữa rồi (... thì ...)." />
  </MUC_TU>
 <MUC_TU Loai_tu="" Noi_dung="chẳng qua">
  <Y_NGHIA Minh_hoa="Chẳng qua vì không hiểu cho nên mới thể." Noi_dung="(dùng làm phần phụ trong câu). Tổ hợp biểu thị mức độ hạn chế của sự việc, cũng chỉ có thế mà thôi (thường hàm ý thanh minh). Chẳng qua chỉ là nói đùa." />
  </MUC_TU>
 <MUC_TU Loai_tu="(khẩu ngữ)." Noi_dung="chẳng trách">
  <Y_NGHIA Minh_hoa="Hư đốn thế, chẳng trách chả ai ưa." Noi_dung="Tổ hợp biểu thị điều vừa nói đến là nguyên nhân tất yếu đã dẫn đến điều, thường là không hay, sắp nêu ra, không có gì phải ngạc nhiên." />
  </MUC_TU>
 <MUC_TU Loai_tu="danh từ" Noi_dung="chặng">
  <Y_NGHIA Minh_hoa="Đi một chặng đường. Bố trí nhiều chặng nghỉ." Noi_dung="Đoạn được chia ra trên con đường dài để tiện bố trí chỗ nghỉ chân." />
  </MUC_TU>
 <MUC_TU Loai_tu="danh từ" Noi_dung="chắp,">
  <Y_NGHIA Minh_hoa="" Noi_dung="Mụn mọc ở rìa mí mắt. Lên chắp. chắp; động từ Làm cho liền lại bằng cách phép vào nhau. Chấp mảnh vỡ. Chấp mối." />
  <Y_NGHIA Minh_hoa="" Noi_dung="úp hoặc nắm hai bàn tay vào nhau." />
  </MUC_TU>
 </GOC>
