<GOC>
 <MUC_TU Loai_tu="động từ" Noi_dung="vần vò">
  <Y_NGHIA Minh_hoa="Bối rối, uỀn uồ chiếc mũ trong tay." Noi_dung="Liên tục xoay trở, vò nắn trong tay." />
  </MUC_TU>
 <MUC_TU Loai_tu="động từ" Noi_dung="vần vũ">
  <Y_NGHIA Minh_hoa="Mây đen uần uũ đây trời. Trời ubỀn uũ đổ mưa." Noi_dung="(Trời mây) chuyển động cuồn cuộn báo hiệu cơn mưa." />
  </MUC_TU>
 <MUC_TU Loai_tu="xem" Noi_dung="vấn vụ (ph.).">
  <Y_NGHIA Minh_hoa="cần uũ." Noi_dung="" />
  </MUC_TU>
 <MUC_TU Loai_tu="động từ" Noi_dung="vần xoay">
  <Y_NGHIA Minh_hoa="Như xoay uằn." Noi_dung="(ít dùng)." />
  </MUC_TU>
 <MUC_TU Loai_tu="danh từ" Noi_dung="vần xuôi">
  <Y_NGHIA Minh_hoa="BA, BE, BÊ, BI là những uân xuôi." Noi_dung="Vằn ghép con chữ phụ âm trước các con chữ nguyên âm trong chữ quốc ngữ, phân biệt với uần ngược." />
  </MUC_TU>
 <MUC_TU Loai_tu="động từ" Noi_dung="vẩn,">
  <Y_NGHIA Minh_hoa="Cá quẫy nước làm bùn uẩn lên. Bầu trời trong không uẩn một gợn mây (bóng (nghĩa bóng)). Lòng vẩn lên một nỗi buồn (bóng (nghĩa bóng))." Noi_dung="Cuộn nổi lên chất bẩn làm mất sự trong lắng." />
  </MUC_TU>
 <MUC_TU Loai_tu="" Noi_dung="vấn,t.">
  <Y_NGHIA Minh_hoa="" Noi_dung="(cũ; ít dùng). Quẩn, không đâu. Nghĩ vẩn." />
  </MUC_TU>
 <MUC_TU Loai_tu="tính từ" Noi_dung="vẩn đục">
  <Y_NGHIA Minh_hoa="Ở trạng thái có nhiều gợn bẩn nổi lên, không trong lắng. Nước bị uẩn đục. Mây đen làm uẩn đục bầu trời. Lòng không hề uẩn đục (bóng (nghĩa bóng))." Noi_dung="" />
  </MUC_TU>
 <MUC_TU Loai_tu="tính từ" Noi_dung="vẩn vơ">
  <Y_NGHIA Minh_hoa="Vấn uơ nghĩ những chuyện không đâu. Hỏi uẩn uơ đủ thứ chuyện. Đi bẩn uơ ngoài đường." Noi_dung="(thường dùng phụ cho động từ). Ở trạng thái suy nghĩ, nói năng hay đi lại mà không có ý thức rõ mình muốn gì, nhằm cái gì, tại sao." />
  </MUC_TU>
 <MUC_TU Loai_tu="phụ từ" Noi_dung="vẫn">
  <Y_NGHIA Minh_hoa="Tôi uẫn ở chỗ cũ. Trời uẫn mua to. Vẫn ông ấy làm chủ nhiệm. Vẫn chứng nào tật ấy. Vẫn thế." Noi_dung="Từ biểu thị sự tiếp tục, tiếp diễn chứ không có gì thay đổi, vào thời điểm nói đến, của một hành động, trạng thái, tính chất nào đó." />
  <Y_NGHIA Minh_hoa="Mưa thì mưa, uẫn đi. Trước nguy hiểm, uẫn bình tĩnh. Chủ nhật, thư uiện uẫn mở cửa." Noi_dung="(dùng phụ trước đg., tính từ). Từ biểu thị ý khẳng định về điều xảy ra, diễn ra như thường, mặc dù điều kiện là không bình thường." />
  <Y_NGHIA Minh_hoa="cái đưa ra để đối chiếu, so sánh, tuy rằng cái này (hay là bản thân cái nói đến) đã được đánh giá là tốt. Vớ kịch này hay thật, nhưng vở trước uẫn hay hơn. Năm nay nó học khá, nhưng uẫn không bằng năm ngoái. Có chuẩn bị trước uẫn hơn." Noi_dung="Từ biểu thị ý khẳng định về một sự đánh giá, cho là hơn (hay là kém)" />
  </MUC_TU>
 <MUC_TU Loai_tu="danh từ" Noi_dung="vẫn thạch">
  <Y_NGHIA Minh_hoa="" Noi_dung="(ít dùng). Thiên thạch." />
  </MUC_TU>
 <MUC_TU Loai_tu="động từ" Noi_dung="vấn,">
  <Y_NGHIA Minh_hoa="Hỏi. Vấn tội. Tự uấn lương tâm." Noi_dung="(kết hợp hạn chế). Quấn thành vòng. Vấn điếu thuốc lá Vấn khăn. Tócuấn trần... vấn, động từ (kết hợp hạn chế)." />
  </MUC_TU>
 <MUC_TU Loai_tu="động từ" Noi_dung="vấn an">
  <Y_NGHIA Minh_hoa="Vấn an cha mẹ." Noi_dung="(cũ; trang trọng). Hỏi thăm sức khoẻ người bê trên." />
  </MUC_TU>
 <MUC_TU Loai_tu="động từ" Noi_dung="vấn danh">
  <Y_NGHIA Minh_hoa="Lễ uấn vấn đáp động từ (kết hợp hạn chế). Hỏi và trả lời (nói khái quát). Bài viết trình bày dưới hình thức uấn đáp. Thi uấn đáp (giám khảo hỏi, thí sinh trả lời bằng miệng)." Noi_dung="(trang trọng). (Nhà trai) đưa lễ vật đến hỏi tên tuổi người con gái (một trong các lễ của tục lệ cưới xin thời xưa)." />
  <Y_NGHIA Minh_hoa="" Noi_dung="(khẩu ngữ). Thi vấn đáp (nói tắt). Vào vấn" />
  </MUC_TU>
 <MUC_TU Loai_tu="danh từ" Noi_dung="vấn đề">
  <Y_NGHIA Minh_hoa="Vấn đề đời sống. Vấn đề dân tộc. Nêu uấn đề. Giải quyết uấn đề. Có uấn đề (kng.; có mâu thuẫn, có điều nào đó cần được giải quyết)." Noi_dung="Điều cằn được xem xét, nghiên cứu, giải quyết." />
  </MUC_TU>
 <MUC_TU Loai_tu="danh từ" Noi_dung="vấn nạn">
  <Y_NGHIA Minh_hoa="Giải quyết uấn nạn. Tham nhũng là một uấn nạn trong xã hội." Noi_dung="Vấn đề khó khăn lớn có tính chất xã hội, đang phải đương đầu đối phó." />
  </MUC_TU>
 <MUC_TU Loai_tu="động từ" Noi_dung="vấn vít">
  <Y_NGHIA Minh_hoa="Những sợi dây leo uấn uít." Noi_dung="Quấn xoắn lại với nhau nhiều vòng." />
  <Y_NGHIA Minh_hoa="Mối sâu uấn uít. Điều uấn vít trong trí." Noi_dung="Vương vấn trong trí, trong lòng." />
  </MUC_TU>
 <MUC_TU Loai_tu="động từ" Noi_dung="vấn vương">
  <Y_NGHIA Minh_hoa="Bao suy nghĩ uấn uương." Noi_dung="Như vuương uấn." />
  </MUC_TU>
 <MUC_TU Loai_tu="danh từ" Noi_dung="vận,">
  <Y_NGHIA Minh_hoa="Vận may. Vận rủi. Gặp uận (kng.; gặp vận may) thì chẳng mấy chốc mà làm nên." Noi_dung="Sự may rủi lớn gặp phải, vốn đã được định sẵn đâu từ trước một cách thân bí theo quan niệm duy tâm." />
  </MUC_TU>
 <MUC_TU Loai_tu="danh từ" Noi_dung="vận,!">
  <Y_NGHIA Minh_hoa="Vần (trong thơ ca). Câu thơ ép uận. II động từ (kng.; ít dùng). Đặt thành câu có vần. Vận ra câu ca dao." Noi_dung="(id.; kết hợp hạn chế)." />
  </MUC_TU>
 <MUC_TU Loai_tu="động từ" Noi_dung="vận,">
  <Y_NGHIA Minh_hoa="" Noi_dung="(ít dùng). Mang đi, chở đi, chuyển đến nơi khác. Vận khí giới và lương thực." />
  <Y_NGHIA Minh_hoa="Vận hết lí lẽ để biện bác." Noi_dung="Đưa hết sức lực ra làm việc gì. Vận hết gân sức ra kéo mà không nối." />
  </MUC_TU>
 <MUC_TU Loai_tu="động từ" Noi_dung="vận,">
  <Y_NGHIA Minh_hoa="Đem chuyện rắng mưa uận uào chuyện đời." Noi_dung="Gán vào, cho như là có quan hệ đến. Chuyện đâu đâu cũng cứ uận uào mình." />
  </MUC_TU>
 <MUC_TU Loai_tu="động từ" Noi_dung="vận,">
  <Y_NGHIA Minh_hoa="" Noi_dung="(phương ngữ). Mặc (quần áo). Vận bộ bà ba đen." />
  </MUC_TU>
 <MUC_TU Loai_tu="động từ" Noi_dung="vận chuyển">
  <Y_NGHIA Minh_hoa="" Noi_dung="Mang chuyển đồ vật nhiều, nặng từ nơi này đến nơi khác tương đối xa, bằng phương tiện hoặc bằng sức loài vật. Vận chuyển hàng. Phương tiện uận chuyển." />
  <Y_NGHIA Minh_hoa="" Noi_dung="(chuyên môn). xem chuyển uận (nghĩa 2)." />
  </MUC_TU>
 <MUC_TU Loai_tu="động từ" Noi_dung="vận dụng">
  <Y_NGHIA Minh_hoa="Vận dụng kiến thức khoa học uào sản xuất." Noi_dung="Đem tri thức lí luận dùng vào thực tiễn. Vận dụng lí luận." />
  </MUC_TU>
 <MUC_TU Loai_tu="động từ" Noi_dung="vận động">
  <Y_NGHIA Minh_hoa="" Noi_dung="(Hiện tượng vật thể) không ngừng thay đổi vị trí trong quan hệ với những vật thể khác." />
  <Y_NGHIA Minh_hoa="Vật chất uận động trong không gian, thời gian. Chuyển động cơ học là dạng uận động đơn giản nhất của uật chất." Noi_dung="(chuyên môn). Từ rất khái quát, dùng để chỉ hình thức tồn tại của vật chất, bao hàm chuyển động, biến đối, phát triển." />
  <Y_NGHIA Minh_hoa="# vận động nên người không được khoẻ." Noi_dung="Hoạt động thay đổi tư thế hay vị trí của thân thể hoặc bộ phận thân thể (nói khái quát, và về mặt tác dụng đến giữ gìn và tăng cường sức khoẻ)." />
  <Y_NGHIA Minh_hoa="Vận động bằng cơ giới. Đánh uận động&quot;." Noi_dung="Di chuyển, thay đổi vị trí trong chiến đấu." />
  <Y_NGHIA Minh_hoa="" Noi_dung="Tuyên truyền, giải thích, động viên làm cho người khác tự nguyện làm việc gì, thường là theo một phong trào nào đó. Vận động nhân dân quyên góp. Vận động bầu" />
  </MUC_TU>
 <MUC_TU Loai_tu="danh từ" Noi_dung="vận động chiến">
  <Y_NGHIA Minh_hoa="" Noi_dung="(cũ). Lối đánh vận động." />
  </MUC_TU>
 <MUC_TU Loai_tu="danh từ" Noi_dung="vận động viên">
  <Y_NGHIA Minh_hoa="Vận động uiên điền kinh. Đạt danh hiệu &quot;Vận động uiên cấp ưu tú”." Noi_dung="Người hoạt động thể thao đã đạt tới một trình độ nhất định. Vận động uiên bơi lội." />
  </MUC_TU>
 <MUC_TU Loai_tu="danh từ" Noi_dung="vận đơn">
  <Y_NGHIA Minh_hoa="" Noi_dung="Chứng từ cấp cho người gửi hàng, xác nhận trách nhiệm chuyên chở hàng tới cảng quy định và giao cho người nhận hàng." />
  </MUC_TU>
 <MUC_TU Loai_tu="danh từ" Noi_dung="vận hạn">
  <Y_NGHIA Minh_hoa="Giúp đỡ nhau trong cơn uận hạn. Gặp uận hạn." Noi_dung="Điều không may lớn gặp phải do số phận (nói khái quát)." />
  </MUC_TU>
 <MUC_TU Loai_tu="động từ" Noi_dung="vận hành">
  <Y_NGHIA Minh_hoa="Bảo đảm cho máy móc uận hành an toàn." Noi_dung="Hoạt động, làm việc hoặc làm cho hoạt động, làm việc (nói về máy móc, thiết bị). Quy tắc uyận hành máy." />
  </MUC_TU>
 <MUC_TU Loai_tu="danh từ" Noi_dung="vận hội">
  <Y_NGHIA Minh_hoa="Vận hội đất nước đến lúc thịnh." Noi_dung="Bước may rủi, thịnh suy lớn được định sẵn đâu từ trước một cách thần bí, theo quan niệm duy tâm." />
  </MUC_TU>
 <MUC_TU Loai_tu="danh từ" Noi_dung="vận khí">
  <Y_NGHIA Minh_hoa="Xem uận khí để bốc thuốc. Vận khí đang suy." Noi_dung="Chiều hướng phát triển tốt, xấu,... của sự vật, sự việc theo quy luật tự nhiên, tại một thời điểm cụ thế, theo thuật phong thủy." />
  </MUC_TU>
 <MUC_TU Loai_tu="xem" Noi_dung="vận mạng (ph.).">
  <Y_NGHIA Minh_hoa="" Noi_dung="uvộn mệnh." />
  </MUC_TU>
 <MUC_TU Loai_tu="danh từ" Noi_dung="vận mệnh">
  <Y_NGHIA Minh_hoa="" Noi_dung="(ít dùng). Như số mệnh." />
  <Y_NGHIA Minh_hoa="Một dân tộc làm chủ uận mệnh của mình." Noi_dung="Cuộc sống nói chung, về mặt những điều hay dở, được mất đang đón chờ." />
  </MUC_TU>
 <MUC_TU Loai_tu="danh từ" Noi_dung="vận số">
  <Y_NGHIA Minh_hoa="Công tỉ uận tải." Noi_dung="Toàn bộ những điều may rủi lớn đã được định sẵn một cách thần bí, theo mê tín. Tiên đoán uận số của một quốc gia. Bốc một quẻ xem uận số thế nào. vận tải động từ Chuyên chở người hoặc đồ vật trên quãng đường tương đối dài. Vận tải hàng hoá. Vận tải đường thuỷ. Máy bay uận tải." />
  </MUC_TU>
 <MUC_TU Loai_tu="danh từ" Noi_dung="vận tốc">
  <Y_NGHIA Minh_hoa="" Noi_dung="Đại lượng vật lí có trị số bằng quãng đường đi được trong đơn vị thời gian. vận trù động từ Tính toán theo vận trù học. Phương án vận trù." />
  </MUC_TU>
 <MUC_TU Loai_tu="danh từ" Noi_dung="vận trù học">
  <Y_NGHIA Minh_hoa="" Noi_dung="Ngành khoa học vận dụng phương pháp toán học và các phương pháp khoa học khác để nghiên cứu và phân tích các vấn đề về sắp xếp, tổ chức." />
  </MUC_TU>
 <MUC_TU Loai_tu="danh từ" Noi_dung="vận văn">
  <Y_NGHIA Minh_hoa="" Noi_dung="(cũ; ít dùng). Văn vần." />
  </MUC_TU>
 <MUC_TU Loai_tu="động từ" Noi_dung="vận xuất">
  <Y_NGHIA Minh_hoa="" Noi_dung="Đưa chuyển ra khỏi nơi khai thác. Vận xuất gỗ bằng trâu kéo. Chọn đường uận xuất ngắn nhất." />
  </MUC_TU>
 <MUC_TU Loai_tu="động từ" Noi_dung="vâng I">
  <Y_NGHIA Minh_hoa="Vâng lời cha mẹ. Vâng lệnh. l\c. Tiếng dùng để đáp lại lời người khác một cách lễ phép, tỏ ý nghe theo, ưng thuận hoặc thừa nhận điều người đối thoại hỏi đến. (- Con ở nhà nhé) - Vâng! (- Mai mới đi?) - Vâng!" Noi_dung="Nghe theo, tuân theo lời sai bảo, dạy bảo." />
  </MUC_TU>
 </GOC>
