<GOC>
 <MUC_TU Loai_tu="tính từ" Noi_dung="hoang phế">
  <Y_NGHIA Minh_hoa="Cảnh chùa hoang phế." Noi_dung="Ở tình trạng bị bỏ hoang lâu ngày. Đất đai hoang phế." />
  </MUC_TU>
 <MUC_TU Loai_tu="động từ" Noi_dung="hoang phí">
  <Y_NGHIA Minh_hoa="Ăn tiêu hoang phí." Noi_dung="(hoặc tính từ). Tiêu dùng rộng rãi, quá mức cần thiết, gây lãng phí. Hoang phí tiền của." />
  </MUC_TU>
 <MUC_TU Loai_tu="tính từ" Noi_dung="hoang sơ">
  <Y_NGHIA Minh_hoa="Thuở hoang sơ. Rừng sâu đây uẻ hoang sơ." Noi_dung="Hoàn toàn hoang dại, như ở thời nguyên thuỷ." />
  </MUC_TU>
 <MUC_TU Loai_tu="tính từ" Noi_dung="hoang tàn">
  <Y_NGHIA Minh_hoa="Cảnh tượng hoang tàn sau trận động đất. hoang thai danh từ Thai chửa hoang." Noi_dung="Hoang vắng và điêu tàn." />
  </MUC_TU>
 <MUC_TU Loai_tu="tính từ" Noi_dung="hoang toảng">
  <Y_NGHIA Minh_hoa="Tính nết hoang toàng. Ăn chơi hoang toàng." Noi_dung="Hoang phí một cách bừa bãi." />
  </MUC_TU>
 <MUC_TU Loai_tu="động từ" Noi_dung="hoang tưởng">
  <Y_NGHIA Minh_hoa="Đó chỉ là điều hoang tưởng. Hoang tưởng là một dạng của bệnh tâm thân." Noi_dung="Tưởng tượng hoàn toàn vô căn cứ điều không thể có trong thực tế." />
  </MUC_TU>
 <MUC_TU Loai_tu="tính từ" Noi_dung="hoang vắng">
  <Y_NGHIA Minh_hoa="Hoang uắng như bãi tha ma." Noi_dung="Vắng bóng người, như bị bỏ hoang." />
  </MUC_TU>
 <MUC_TU Loai_tu="tính từ" Noi_dung="hoang vu">
  <Y_NGHIA Minh_hoa="" Noi_dung="ở trạng thái bỏ không, để cho cây cỏ mọc tự nhiên, chưa hề có tác động của con người. Rừng núi hoang bu." />
  </MUC_TU>
 <MUC_TU Loai_tu="danh từ" Noi_dung="hoàng">
  <Y_NGHIA Minh_hoa="Sống như ông hoàng." Noi_dung="Hoàng tử (nói tắt)." />
  </MUC_TU>
 <MUC_TU Loai_tu="xem" Noi_dung="hoàng anh">
  <Y_NGHIA Minh_hoa="" Noi_dung="vàng anh." />
  </MUC_TU>
 <MUC_TU Loai_tu="danh từ" Noi_dung="hoàng ân">
  <Y_NGHIA Minh_hoa="" Noi_dung="(cũ). Ơn vua." />
  </MUC_TU>
 <MUC_TU Loai_tu="danh từ" Noi_dung="hoàng bá">
  <Y_NGHIA Minh_hoa="" Noi_dung="Cây có lá kép lông chim, hoa vàng, vỏ cây dùng làm thuốc." />
  </MUC_TU>
 <MUC_TU Loai_tu="danh từ" Noi_dung="hoàng bào">
  <Y_NGHIA Minh_hoa="" Noi_dung="Áo triều phục màu vàng của vua." />
  </MUC_TU>
 <MUC_TU Loai_tu="danh từ" Noi_dung="hoàng cầm">
  <Y_NGHIA Minh_hoa="" Noi_dung="Cây thân cỏ cùng họ với bạc hà, lá hình mác hẹp, mọc đối, hoa màu xanh tím, mọc thành bông ở đầu cành, rễ dùng làm thuốc." />
  </MUC_TU>
 <MUC_TU Loai_tu="danh từ" Noi_dung="hoàng cung">
  <Y_NGHIA Minh_hoa="" Noi_dung="Cung vua," />
  </MUC_TU>
 <MUC_TU Loai_tu="danh từ" Noi_dung="hoàng đàn">
  <Y_NGHIA Minh_hoa="" Noi_dung="Cây hạt trần mọc ở núi cao, tán láhìnhlọng, gỗ quý, dùng để đóng đồ đạc. hoàng đản danh từ Bệnh vàng da do thấm sắc tổ mật." />
  </MUC_TU>
 <MUC_TU Loai_tu="danh từ" Noi_dung="hoàng đạo">
  <Y_NGHIA Minh_hoa="" Noi_dung="Quĩ đạo chuyển động biểu kiến của Mặt Trời trên nên sao." />
  </MUC_TU>
 <MUC_TU Loai_tu="danh từ" Noi_dung="hoàng đố">
  <Y_NGHIA Minh_hoa="" Noi_dung="Vua của một nước lớn, thường được nhiều nước xung quanh thần phục." />
  </MUC_TU>
 <MUC_TU Loai_tu="danh từ" Noi_dung="hoàng đới">
  <Y_NGHIA Minh_hoa="" Noi_dung="Dải thiên cầu, nằm hai bên hoàng đạo." />
  </MUC_TU>
 <MUC_TU Loai_tu="danh từ" Noi_dung="hoàng gia">
  <Y_NGHIA Minh_hoa="" Noi_dung="Như hoàng phái." />
  </MUC_TU>
 <MUC_TU Loai_tu="danh từ" Noi_dung="hoàng giáp">
  <Y_NGHIA Minh_hoa="" Noi_dung="Học vị của người đỗ dưới thám hoa trong khoa thi đình." />
  </MUC_TU>
 <MUC_TU Loai_tu="danh từ" Noi_dung="hoàng hậu">
  <Y_NGHIA Minh_hoa="" Noi_dung="Vợ cả của vua." />
  </MUC_TU>
 <MUC_TU Loai_tu="danh từ" Noi_dung="hoàng hôn">
  <Y_NGHIA Minh_hoa="" Noi_dung="Khoảng thời gian mặt trời mới lặn, ánh sáng yếu ớt và mờ dần. Bóng hoàng hôn. Hoàng hôn vừa xuống. Buổi hoàng hôn của cuộc đời (bóng (nghĩa bóng))." />
  </MUC_TU>
 <MUC_TU Loai_tu="danh từ" Noi_dung="hoàng kì cũng viết hoàng kỳ.">
  <Y_NGHIA Minh_hoa="" Noi_dung="Cây bò thuộc họ đậu, lá kép lông chim, rễ phỏng to, dùng làm thuốc." />
  </MUC_TU>
 <MUC_TU Loai_tu="danh từ" Noi_dung="hoàng kim">
  <Y_NGHIA Minh_hoa="Thời kì hoàng kim của Hi Lạp cổ đại." Noi_dung="(dùng phụ sau danh từ trong một số tổ hợp). Vàng; dùng để ví sự phồn thịnh cao nhất, đẹp nhất của một nền văn minh, một thời đại, một thời kì (thường là đã qua)." />
  </MUC_TU>
 <MUC_TU Loai_tu="xem" Noi_dung="hoàng kỳ">
  <Y_NGHIA Minh_hoa="" Noi_dung="hoàng kì." />
  </MUC_TU>
 <MUC_TU Loai_tu="danh từ" Noi_dung="hoàng lan">
  <Y_NGHIA Minh_hoa="" Noi_dung="Cây to cùng họ với na, mặt dưới lá hơi có lông, hoa thơm, màu vàng lục." />
  </MUC_TU>
 <MUC_TU Loai_tu="danh từ" Noi_dung="hoàng liên">
  <Y_NGHIA Minh_hoa="" Noi_dung="Cây thân cỏ, thân mọc ngằm dưới đất, lá kép, mọc cách, hoa màu trắng, thân rễ có vị đắng, dùng làm thuốc." />
  </MUC_TU>
 <MUC_TU Loai_tu="danh từ" Noi_dung="hoàng phái">
  <Y_NGHIA Minh_hoa="" Noi_dung="Họ hàng của vua. Người trong hoàng phái." />
  </MUC_TU>
 <MUC_TU Loai_tu="danh từ" Noi_dung="hoàng thái hậu">
  <Y_NGHIA Minh_hoa="" Noi_dung="xem thái hậu." />
  </MUC_TU>
 <MUC_TU Loai_tu="danh từ" Noi_dung="hoàng thái tử">
  <Y_NGHIA Minh_hoa="xem thái tử." Noi_dung="" />
  </MUC_TU>
 <MUC_TU Loai_tu="danh từ" Noi_dung="hoàng thành">
  <Y_NGHIA Minh_hoa="" Noi_dung="Nơi vua ở và triều đình làm việc, có thành bao bọc. ." />
  </MUC_TU>
 <MUC_TU Loai_tu="danh từ" Noi_dung="hoàng thân">
  <Y_NGHIA Minh_hoa="" Noi_dung="Người có họ gần (chú bác, anh em ruột) với vua." />
  </MUC_TU>
 <MUC_TU Loai_tu="danh từ" Noi_dung="hoàng thất">
  <Y_NGHIA Minh_hoa="" Noi_dung="Như hoàng phái." />
  </MUC_TU>
 <MUC_TU Loai_tu="danh từ" Noi_dung="hoàng thiên">
  <Y_NGHIA Minh_hoa="" Noi_dung="(cũ). Trời, coi là đấng tối cao." />
  </MUC_TU>
 <MUC_TU Loai_tu="danh từ" Noi_dung="hoàng thổ">
  <Y_NGHIA Minh_hoa="" Noi_dung="Đất màu vàng, hạt mịn, bở, xốp, dễ thấm nước." />
  </MUC_TU>
 <MUC_TU Loai_tu="danh từ" Noi_dung="hoàng thượng">
  <Y_NGHIA Minh_hoa="" Noi_dung="Từ dùng để gọi vua một cách tôn kính." />
  </MUC_TU>
 <MUC_TU Loai_tu="danh từ" Noi_dung="hoàng tinh,">
  <Y_NGHIA Minh_hoa="" Noi_dung="Củ dong." />
  </MUC_TU>
 <MUC_TU Loai_tu="" Noi_dung="hoàng tỉnh, `d.">
  <Y_NGHIA Minh_hoa="" Noi_dung="Cây thuộc họ hành tỏi, thân rễ hơi giống củ gừng, dùng làm thuốc." />
  </MUC_TU>
 <MUC_TU Loai_tu="danh từ" Noi_dung="hoàng tộc">
  <Y_NGHIA Minh_hoa="" Noi_dung="Như hoàng phái." />
  </MUC_TU>
 <MUC_TU Loai_tu="danh từ" Noi_dung="hoàng tôn">
  <Y_NGHIA Minh_hoa="" Noi_dung="Cháu nội trai của vua." />
  </MUC_TU>
 <MUC_TU Loai_tu="danh từ" Noi_dung="hoàng triều">
  <Y_NGHIA Minh_hoa="" Noi_dung="Triều đình của vua đang hoàng trùng danh từ (cũ). Châu chấu." />
  </MUC_TU>
 <MUC_TU Loai_tu="danh từ" Noi_dung="hoàng tuyền">
  <Y_NGHIA Minh_hoa="" Noi_dung="(cũ; văn chương). Suối vàng." />
  </MUC_TU>
 <MUC_TU Loai_tu="danh từ" Noi_dung="hoàng tử">
  <Y_NGHIA Minh_hoa="" Noi_dung="Con trai vua." />
  </MUC_TU>
 <MUC_TU Loai_tu="danh từ" Noi_dung="hoàng yến">
  <Y_NGHIA Minh_hoa="" Noi_dung="Chim nhỏ cùng họ với bạch yến, lông màu vàng nhạt, nuôi làm cảnh." />
  <Y_NGHIA Minh_hoa="" Noi_dung="Màu vàng nhạt như màu lông hoàng yến." />
  </MUC_TU>
 <MUC_TU Loai_tu="động từ" Noi_dung="hoảng">
  <Y_NGHIA Minh_hoa="Nghe tiếng quát, hoảng quá chạy mất." Noi_dung="(hay tính từ). Ở trạng thái mất tự chủ đột ngột, do bị tác động của một đe doạ bất ngờ." />
  </MUC_TU>
 <MUC_TU Loai_tu="động từ" Noi_dung="hoảng hồn">
  <Y_NGHIA Minh_hoa="Hoảng hồn, rụng rời chân tay. Bị một phen hoảng hồn." Noi_dung="(hay tính từ). Hoảng sợ đến mức mất cả tỉnh thần, hồn vía." />
  </MUC_TU>
 <MUC_TU Loai_tu="động từ" Noi_dung="hoảng hốt">
  <Y_NGHIA Minh_hoa="Hoảng hốt chạy tán loạn." Noi_dung="(hay tính từ). Hoảng (nói khái quát). Nét mặt hoảng hốt." />
  </MUC_TU>
 <MUC_TU Loai_tu="động từ" Noi_dung="hoảng loạn">
  <Y_NGHIA Minh_hoa="Tâm thần hoảng loạn. Những tiếng kêu hoảng loạn." Noi_dung="Hoảng tới mức có những biểu hiện mất trí." />
  </MUC_TU>
 <MUC_TU Loai_tu="động từ" Noi_dung="hoảng sợ">
  <Y_NGHIA Minh_hoa="Nghe tiếng nổ, con ngựa hoảng sợ chạy lông lên." Noi_dung="(hoặc tính từ). Ở trạng thái mất tự chủ đột ngột do sợ hãi trước đe doạ bất ngờ." />
  </MUC_TU>
 <MUC_TU Loai_tu="xem" Noi_dung="hoãng (ph.).">
  <Y_NGHIA Minh_hoa="" Noi_dung="hoằng." />
  </MUC_TU>
 <MUC_TU Loai_tu="động từ" Noi_dung="hoáng,">
  <Y_NGHIA Minh_hoa="" Noi_dung="(hay tính từ). (ph.; ít dùng). Hơi hoảng." />
  </MUC_TU>
 <MUC_TU Loai_tu="tính từ" Noi_dung="hoáng;">
  <Y_NGHIA Minh_hoa="" Noi_dung="(phương ngữ). Hoa (mắt). Mắt cứ hoáng lên, tìm mãi mà không thấy." />
  </MUC_TU>
 <MUC_TU Loai_tu="" Noi_dung="hoángst.">
  <Y_NGHIA Minh_hoa="Bức hoành sơn son. II\ tính từ (ịd.). (Chiều) ngang. Bê hoành." Noi_dung="(ph.; ít dùng). Nhảm. Tín đồn hoáng. hoành ! danh từ Cây tre hoặc đoạn gỗ tròn gác ngang để đóng rui lợp mái nhà theo kiến trúc cổ truyền. II danh từ Hoành phi (nói tắt)." />
  </MUC_TU>
 <MUC_TU Loai_tu="danh từ" Noi_dung="hoành cách">
  <Y_NGHIA Minh_hoa="" Noi_dung="Hoành cách mô (nói tắt)." />
  </MUC_TU>
 <MUC_TU Loai_tu="" Noi_dung="hoành cách mô d.x cơhoành.">
  <Y_NGHIA Minh_hoa="" Noi_dung="" />
  </MUC_TU>
 <MUC_TU Loai_tu="danh từ" Noi_dung="hoành độ">
  <Y_NGHIA Minh_hoa="" Noi_dung="Số thứ nhất trong cặp số dùng để xác định vị trí của một điểm trong mặt phẳng toạ độ (bằng số đo vector đi từ gốc toạ độ đến hình chiếu điểm ấy trên trục hoành)." />
  </MUC_TU>
 <MUC_TU Loai_tu="động từ" Noi_dung="hoành hành">
  <Y_NGHIA Minh_hoa="Giặc cướp hoành hành. Dịch cúm hoành hành (bóng (nghĩa bóng))." Noi_dung="Làm nhiều điều ngang ngược một cách tuỳ ý trên phạm vi rộng lớn." />
  </MUC_TU>
 <MUC_TU Loai_tu="danh từ" Noi_dung="hoành phi">
  <Y_NGHIA Minh_hoa="" Noi_dung="Biển gỗ có khắc chữ Hán lớn, thường treo ngang giữa gian nhà để thờ hoặc trang trí." />
  </MUC_TU>
 <MUC_TU Loai_tu="tính từ" Noi_dung="hoành tráng">
  <Y_NGHIA Minh_hoa="Tranh hoành tráng. Nghệ thuật hoành tráng." Noi_dung="(Tranh, tượng, v.v.) có quy mô đồ sộ nhằm thể hiện những đề tài lớn." />
  </MUC_TU>
 <MUC_TU Loai_tu="động từ" Noi_dung="hoành triệt">
  <Y_NGHIA Minh_hoa="Hoành triệt các cống." Noi_dung="Lấp kín để chặn ngang không cho nước chảy qua." />
  </MUC_TU>
 <MUC_TU Loai_tu="động từ" Noi_dung="hoạnh">
  <Y_NGHIA Minh_hoa="" Noi_dung="(ít dùng). Hoạnh hoẹ (nói tắt)." />
  </MUC_TU>
 <MUC_TU Loai_tu="động từ" Noi_dung="hoạnh hoẹ">
  <Y_NGHIA Minh_hoa="Thích hoạnh hoẹ mọi người. Lên giọng hoạnh hop." Noi_dung="Bắt bẻ điều này điều nọ để ra oai, làm khó dễ cho người khác." />
  </MUC_TU>
 <MUC_TU Loai_tu="động từ" Noi_dung="hoạnh phát">
  <Y_NGHIA Minh_hoa="" Noi_dung="(cũ; ít dùng). Trở nên giàu có nhanh chóng bằng cách không chính đáng hoặc nhờ gặp may." />
  </MUC_TU>
 <MUC_TU Loai_tu="danh từ" Noi_dung="hoạnh tài">
  <Y_NGHIA Minh_hoa="Bước đi hoạt. Bước lên diễn đàn, trông anh hoạt hẳn lên." Noi_dung="(cũ; ít dùng). Tiền của kiếm được bằng cách không chính đáng hoặc do gặp hoạt tính từ (ít dùng). Nhanh nhẹn, tỏ ra rất có sinh khí." />
  <Y_NGHIA Minh_hoa="Văn uiết rất hoạt." Noi_dung="(Nét vẽ hoặc lời văn) thanh thoát, lưu loát. Nét vẽ hoạt." />
  </MUC_TU>
 <MUC_TU Loai_tu="danh từ" Noi_dung="hoạt bản">
  <Y_NGHIA Minh_hoa="" Noi_dung="Bắn in bằng chữ rời chắp lại." />
  </MUC_TU>
 <MUC_TU Loai_tu="tính từ" Noi_dung="hoạt bát">
  <Y_NGHIA Minh_hoa="Ăn nói hoạt bát. Cứ chỉ hoạt bát. Một thanh niên hoạt bát." Noi_dung="Lanh lợi trong nói năng, ứng đáp, nhanh nhẹn trong cử chỉ, động tác." />
  </MUC_TU>
 <MUC_TU Loai_tu="danh từ" Noi_dung="hoạt cảnh">
  <Y_NGHIA Minh_hoa="" Noi_dung="Hình thức nghệ thuật sân khấu ngắn, nhẹ, phản ánh một cảnh sinh hoạt xã hội." />
  </MUC_TU>
 <MUC_TU Loai_tu="danh từ" Noi_dung="hoạt chất">
  <Y_NGHIA Minh_hoa="Một cây thuốc chứa nhiều hoạt chất." Noi_dung="Chất có tác dụng đối với cơ thể sinh vật." />
  </MUC_TU>
 <MUC_TU Loai_tu="tính từ" Noi_dung="hoạt đầu">
  <Y_NGHIA Minh_hoa="Phần tử hoạt đầu." Noi_dung="(cũ). Cơ hội chủ nghĩa (hàm ý khinh)." />
  </MUC_TU>
 </GOC>
