<GOC>
 <MUC_TU Loai_tu="danh từ" Noi_dung="quang âm">
  <Y_NGHIA Minh_hoa="" Noi_dung="(cũ). Ánh sáng (ban ngày) và bóng tối (ban đêm); dùng (văn chương) để chỉ thời gian, ngày giờ. Quang âm thấm thoát." />
  </MUC_TU>
 <MUC_TU Loai_tu="danh từ" Noi_dung="quang cảnh">
  <Y_NGHIA Minh_hoa="" Noi_dung="Cảnh bày ra trước mắt. Quang cảnh đông Vui của phiên chợ. Quang cảnh nông thôn đổi mới." />
  </MUC_TU>
 <MUC_TU Loai_tu="danh từ" Noi_dung="quang cầu">
  <Y_NGHIA Minh_hoa="Lớp thấp của khí quyển Mặt Trời, nguồn gốc của toàn bộ bức xạ Mặt Trời quan sát được." Noi_dung="" />
  </MUC_TU>
 <MUC_TU Loai_tu="danh từ" Noi_dung="quang dẫn">
  <Y_NGHIA Minh_hoa="" Noi_dung="Hiện tượng tăng độ dẫn điện của một số chất khi nó được chiếu sáng." />
  </MUC_TU>
 <MUC_TU Loai_tu="danh từ" Noi_dung="quang dầu">
  <Y_NGHIA Minh_hoa="" Noi_dung="Chất liệu trong và bóng, chế từ nhựa thông, dùng quét lên đồ vật để tăng độ bền và vẻ đẹp." />
  </MUC_TU>
 <MUC_TU Loai_tu="động từ" Noi_dung="quang dầu">
  <Y_NGHIA Minh_hoa="" Noi_dung="Quét lên một lớp quang dầu để làm tăng độ bên và vẻ đẹp. Quang dầu chiếc nón." />
  </MUC_TU>
 <MUC_TU Loai_tu="tính từ" Noi_dung="quang đãng">
  <Y_NGHIA Minh_hoa="Bầu trời quang đãng." Noi_dung="Sáng sủa và có vẻ rộng rãi." />
  </MUC_TU>
 <MUC_TU Loai_tu="danh từ" Noi_dung="quang điện">
  <Y_NGHIA Minh_hoa="" Noi_dung="Điện tích (điện tử, ion dương) xuất hiện dưới tác dụng của ánh sáng và do đó vật trở nên dẫn điện. Bộ biến đổi quang điện. Sản phẩm quang điện." />
  </MUC_TU>
 <MUC_TU Loai_tu="danh từ" Noi_dung="quang gánh">
  <Y_NGHIA Minh_hoa="" Noi_dung="Quang và đòn gánh (nói khái quát). Đặt quang gánh xuống nghỉ. Chuẩn bị quang gánh." />
  </MUC_TU>
 <MUC_TU Loai_tu="danh từ" Noi_dung="quang học">
  <Y_NGHIA Minh_hoa="" Noi_dung="Bộ môn vật lí học nghiên cứu về ánh sáng và tương tác của ánh sáng với vật chất." />
  </MUC_TU>
 <MUC_TU Loai_tu="danh từ" Noi_dung="quang hợp">
  <Y_NGHIA Minh_hoa="" Noi_dung="Quá trình tạo thành các chất hữu cơ trong thực vật và vi khuẩn nhờ carbon của các hợp chất vô cơ và dưới tác dụng của ánh sáng." />
  </MUC_TU>
 <MUC_TU Loai_tu="tính từ" Noi_dung="quang minh">
  <Y_NGHIA Minh_hoa="" Noi_dung="(ít dùng). Rõ ràng, sáng tỏ." />
  </MUC_TU>
 <MUC_TU Loai_tu="tính từ" Noi_dung="quang minh chính đại">
  <Y_NGHIA Minh_hoa="" Noi_dung="Ngay thẳng, rõ ràng, không chút mờ ám. Việc làm quang minh chính đại." />
  </MUC_TU>
 <MUC_TU Loai_tu="danh từ" Noi_dung="quang phổ">
  <Y_NGHIA Minh_hoa="" Noi_dung="Dải sáng nhiều màu thu được khi phân tích chùm ánh sáng phức tạp bằng một dụng cụ thích hợp (như lăng kính, v.v.)." />
  </MUC_TU>
 <MUC_TU Loai_tu="động từ" Noi_dung="quang quác">
  <Y_NGHIA Minh_hoa="" Noi_dung="Từ mô phỏng tiếng kêu liên tiếp của gà, ngỗng và một số loại chim lớn." />
  <Y_NGHIA Minh_hoa="" Noi_dung="iếng gà vịt quang quác." />
  <Y_NGHIA Minh_hoa="Mồm cứ quang quác như qua. Quang quác cái môm, ai chịu nối." Noi_dung="(thông tục). Nói, la rất to, gây cảm giác khó chịu." />
  </MUC_TU>
 <MUC_TU Loai_tu="tính từ" Noi_dung="quang quẻ">
  <Y_NGHIA Minh_hoa="" Noi_dung="Quang (nói khái quát). Bầu trời quang quẻ. 7)ường sá quang quế." />
  </MUC_TU>
 <MUC_TU Loai_tu="danh từ" Noi_dung="quang sai">
  <Y_NGHIA Minh_hoa="" Noi_dung="Sai sót của một hệ quang học (gương, thấu kính, v.v.) khiến cho ảnh do chúng tạo ra không hoàn toàn giống như vật." />
  </MUC_TU>
 <MUC_TU Loai_tu="danh từ" Noi_dung="quang tuyến">
  <Y_NGHIA Minh_hoa="Quang tuyến X." Noi_dung="(cũ). Tia." />
  </MUC_TU>
 <MUC_TU Loai_tu="tính từ" Noi_dung="quang vinh">
  <Y_NGHIA Minh_hoa="" Noi_dung="Như vinh quang. Sự nghiệp quang uinh." />
  </MUC_TU>
 <MUC_TU Loai_tu="động từ" Noi_dung="quàng,">
  <Y_NGHIA Minh_hoa="Em bé quàng lấy cổ mẹ. Quàng tay nhau. Ôm quàng." Noi_dung="Vòng cánh tay ôm qua người hay qua vai, qua cổ người khác." />
  <Y_NGHIA Minh_hoa="Quàng khăn. Quàng tấm nylon che mưa. Súng quàng uai." Noi_dung="Mang vào thân mình bằng cách quấn hoặc vòng qua người, qua đầu" />
  <Y_NGHIA Minh_hoa="Vướng phải, mắc phải khi đang đi. Đi đâu mà uội mà uàng, Mà uấp phải đá mà quàng phải dây (ca dao)." Noi_dung="(ít dùng)." />
  </MUC_TU>
 <MUC_TU Loai_tu="phụ từ" Noi_dung="quàng,">
  <Y_NGHIA Minh_hoa="Làm quàng lên!" Noi_dung="(khẩu ngữ). Một cách nhanh, vội, cốt cho xong để làm việc khác. Ăn quàng mấy lưng cơm rồi đi." />
  <Y_NGHIA Minh_hoa="Thấy người sang bắt quàng làm họ (tmg.)." Noi_dung="(kết hợp hạn chế). Không kể gì đúng sai. Nói quàng Vơ quàng." />
  </MUC_TU>
 <MUC_TU Loai_tu="động từ" Noi_dung="quàng quạc">
  <Y_NGHIA Minh_hoa="" Noi_dung="Từ mô phỏng tiếng kêu liên tiếp của vịt, ngỗng." />
  <Y_NGHIA Minh_hoa="" Noi_dung="(thợt). Như quang quác (nghĩa 2)." />
  </MUC_TU>
 <MUC_TU Loai_tu="tính từ" Noi_dung="quàng xiên">
  <Y_NGHIA Minh_hoa="" Noi_dung="Bậy bạ, không chút gì đúng đắn cả (thường nói về sự nói năng). Ăn nói quàng xiên. Chuyện mê tín quàng xiên." />
  </MUC_TU>
 <MUC_TU Loai_tu="động từ" Noi_dung="quảng bá">
  <Y_NGHIA Minh_hoa="" Noi_dung="(ít dùng). Phố biến rộng rãi bằng các phương tiện thông tin." />
  </MUC_TU>
 <MUC_TU Loai_tu="động từ" Noi_dung="quảng canh">
  <Y_NGHIA Minh_hoa="" Noi_dung="(Phương thức canh tác) dựa chủ yếu vào việc mở rộng diện tích trồng trọt để tăng sản lượng nông nghiệp; trái với thâm canh." />
  </MUC_TU>
 <MUC_TU Loai_tu="động từ" Noi_dung="quảng cáo">
  <Y_NGHIA Minh_hoa="" Noi_dung="(hoặc danh từ). Trình bày để giới thiệu rộng rãi cho nhiều người biết nhằm tranh thủ được nhiều khách hàng. Quảng cáo các mặt hàng Dán apphich quảng cáo phùm. Đăng quảng cáo trên báo." />
  </MUC_TU>
 <MUC_TU Loai_tu="tính từ" Noi_dung="quảng đại">
  <Y_NGHIA Minh_hoa="Quảng đại quần chúng." Noi_dung="(Quần chúng, nhân dân) đông đảo, rộng lớn." />
  <Y_NGHIA Minh_hoa="" Noi_dung="(cũ). (Tấm lòng) rộng rãi, độ lượng." />
  </MUC_TU>
 <MUC_TU Loai_tu="động từ" Noi_dung="quảng giao">
  <Y_NGHIA Minh_hoa="Giao thiệp rộng." Noi_dung="(cũ; ít dùng)." />
  </MUC_TU>
 <MUC_TU Loai_tu="danh từ" Noi_dung="quảng trường">
  <Y_NGHIA Minh_hoa="" Noi_dung="Khu đất trống, rộng trong thành phố, xung quanh thường có những kiến trúc thích hợp." />
  </MUC_TU>
 <MUC_TU Loai_tu="danh từ" Noi_dung="quãng">
  <Y_NGHIA Minh_hoa="Quzãng đường. Đi cách nhau một quãng. Quấãng đời xưa. Làm cách quãng. 2 (khẩu ngữ). Phần không gian hoặc thời gian tương đối ngắn được xác định đại khái. Vào quãng năm giờ chiều. Em bé quãng năm-bdy tuổi. 3 (chuyên môn). Khoảng cách giữa hai nốt nhạc, tính bằng cung và nửa cung, và gọi theo số bậc giữa hai nốt đó." Noi_dung="† Phần không gian hoặc thời gian tương đối ngắn được xác định giữa hai điểm hoặc hai thời điểm." />
  </MUC_TU>
 <MUC_TU Loai_tu="tính từ" Noi_dung="quáng">
  <Y_NGHIA Minh_hoa="Sáng quá làm quáng cả mắt. Mắt bị quáng đèn. Đang ở ngoài nắng bước uào buồng tối, bị quáng chẳng nhìn thấy gì." Noi_dung="ở trạng thái thị giác bị rối loạn, trông không rõ do tác động của một sự thay đối quá đột ngột cường độ ánh sáng." />
  </MUC_TU>
 <MUC_TU Loai_tu="tính từ" Noi_dung="quáng gà">
  <Y_NGHIA Minh_hoa="Mắc bệnh quáng gà." Noi_dung="(Mắt) ở tình trạng nhìn không rõ lúc tranh tối tranh sáng." />
  </MUC_TU>
 <MUC_TU Loai_tu="tính từ" Noi_dung="quáng quàng">
  <Y_NGHIA Minh_hoa="Nhảy quáng quàng xuống đất. Ăn quáng ăn quàng mấy miếng rồi đi ngay." Noi_dung="(kng.; thường dùng phụ cho động từ). Vội vàng, hấp tấp." />
  </MUC_TU>
 <MUC_TU Loai_tu="danh từ" Noi_dung="quanh">
  <Y_NGHIA Minh_hoa="Luỹ tre quanh làng Ngồi vây quanh bếp lửa Vòng quanh*." Noi_dung="(thường dùng trước danh từ). Phần bao phía ngoài của một vị trí, nơi chốn nào đó. Rào giậu quanh uườn." />
  <Y_NGHIA Minh_hoa="ai không. Tìm quanh đâu đó. Chắc chỉ ở quanh đây thôi (ở chỗ nào đó quanh đây). Dạo quanh." Noi_dung="(thường dùng phụ sau đg,). Những nơi ở gần, làm thành như một vòng bao phía ngoài (nói tổng quát). Nhìn quanh xem có thấy" />
  </MUC_TU>
 <MUC_TU Loai_tu="động từ" Noi_dung="quanh">
  <Y_NGHIA Minh_hoa="QuÃng đường quanh quanh. Khúc quanh của dòng sông. Đường đi quanh." Noi_dung="Di chuyển theo đường vòng. Xe đang quanh theo chiều quy định. II tính từ (Đường sá, sông ngòi) vòng lượn, uốn khúc." />
  <Y_NGHIA Minh_hoa="Chối quanh. Giấu quanh, không chịu nói." Noi_dung="(thường dùng phụ sau động từ). (Nói) xa xa gần gần, tránh không đi thẳng vào vấn đề." />
  </MUC_TU>
 <MUC_TU Loai_tu="tính từ" Noi_dung="quanh co">
  <Y_NGHIA Minh_hoa="" Noi_dung="(hoặc động từ). (Dường sá, sông ngòi) vòng lượn, uốn khúc nhiều, không thẳng. Đường núi quanh co khúc khuỷu. Dòng suối lượn quanh co theo ghênh đá." />
  <Y_NGHIA Minh_hoa="Thái độ quanh co. Chối cãi quanh co. Nhận đi, đừng quanh co nữa!" Noi_dung="Loanh quanh mãi, có ý giấu giếm." />
  </MUC_TU>
 <MUC_TU Loai_tu="danh từ" Noi_dung="quanh năm">
  <Y_NGHIA Minh_hoa="Có hoa quanh năm." Noi_dung="Suốt từ đầu năm đến cuối năm." />
  </MUC_TU>
 <MUC_TU Loai_tu="động từ" Noi_dung="quanh quẩn">
  <Y_NGHIA Minh_hoa="Quanh quẩn ở nhà suốt ngày. Nhìn quanh quấn." Noi_dung="(hoặc tính từ). Loanh quanh ở một chỗ, không rời đi đâu xa. Chơi quanh quấn ngoài sân." />
  <Y_NGHIA Minh_hoa="cứ quanh quần trong đầu. Nghĩ quanh quần mãi mà uẫn chưa quyết định được." Noi_dung="(Suy nghĩ) trở đi trở lại như cũ, không dứt, không thoát ra được. Những ý nghĩ" />
  <Y_NGHIA Minh_hoa="Quanh quần chỉ có bấy nhiêu uiệc. Quanh đi quần lại uẫn thế." Noi_dung="(dùng không có chủ ngữ). Trở đi trở lại, rốt cuộc." />
  </MUC_TU>
 <MUC_TU Loai_tu="danh từ" Noi_dung="quanh quất">
  <Y_NGHIA Minh_hoa="Nhìn quanh quất như tìm cái gì. Ngó quanh ngó quất. Ở quanh quất đâu đây." Noi_dung="Quanh nơi nào đó, không xa." />
  </MUC_TU>
 <MUC_TU Loai_tu="tính từ" Noi_dung="quanh quất">
  <Y_NGHIA Minh_hoa="" Noi_dung="(danh từ). Quanh co, không thẳng. Đường đi quanh quất trong làng." />
  </MUC_TU>
 <MUC_TU Loai_tu="tính từ" Noi_dung="quanh quéo">
  <Y_NGHIA Minh_hoa="Tìm quanh quéo. Quanh quéo chỗ này, không đi đâu." Noi_dung="(hoặc đg,). (khẩu ngữ). Ở quanh đâu đó." />
  <Y_NGHIA Minh_hoa="quanh co. Đường đi quanh quéo. Nói quanh quéo." Noi_dung="Như" />
  </MUC_TU>
 <MUC_TU Loai_tu="động từ" Noi_dung="quành">
  <Y_NGHIA Minh_hoa="Quành ra sau nhà. Bay quành trở lại. Quành xe. Khúc đường quành." Noi_dung="Không theo hướng thẳng mà vòng lại, hoặc quanh sang một bên." />
  </MUC_TU>
 <MUC_TU Loai_tu="tính từ" Noi_dung="quánh">
  <Y_NGHIA Minh_hoa="Hồ quánh. Đặc quánh. Khô quánh." Noi_dung="Ở trạng thái đặc sệt như dính lại với nhau thành khối." />
  </MUC_TU>
 <MUC_TU Loai_tu="tính từ" Noi_dung="quạnh">
  <Y_NGHIA Minh_hoa="" Noi_dung="Vắng và yên lặng đến mức gây cảm giác trống trải, buồn bã. Có thêm" />
  </MUC_TU>
 </GOC>
